Workbook

Sheet Prospects
A1: City | B1: Business Name | C1: Phone | D1: Has Website | E1: Website URL | F1: Website Quality | G1: Google Rating | H1: Review Count | I1: Flag | J1: Owner Name | K1: Notes | L1: Source | M1: Date Found | N1: Contacted (Y/N) | O1: Contact Date | P1: Response / Outcome
A2: Arlington | B2: Service Max Heating & Air Conditioning, LLC | C2: (360) 333-5904 | D2: Yes (broken) | E2: servicemaxheating.com | F2: Broken / not loading | G2: 4.6 | H2: 46 | I2: Warm | J2: Mike Raether | K2: Domain exists but site failed to load on repeated visits (error page) - effectively no working web presence. Family-owned since 2012 | L2: Google Maps; WebSearch; direct site visit | M2: 2026-07-02 | N2: Y | O2: 2026-07-14 | P2: Went to voicemail — call again (owner voicemail = good sign) | July 14 — 2nd voicemail left. Said: second time calling, know you're busy, have something to let customers book when they can't reach you. Left callback # 425-309-9782.
A3: Arlington | B3: A-Service: Heating, Cooling & Appliance Repair Arlington | C3: (360) 859-8185 | D3: No | E3: N/A | F3: N/A | G3: 5 | H3: 169 | I3: Hot | J3: 3rd-gen technician (name not confirmed) | K3: No dedicated business website found. Top search result for the name (services-wa.com) is an unrelated Eastern WA business with a different phone number and review count. Relies on Google + Nextdoor listing only | L3: Google Maps; WebSearch; Nextdoor | M3: 2026-07-02 | N3: Y | O3: 2026-07-14 | P3: Called — AI answering system, no human reached. Call again. | July 14 — AI agent again, no human reached. Try early morning or after 5pm.
A4: Arlington | B4: AeroCool Heating and Air Conditioning | C4: (425) 405-4876 | D4: Yes | E4: aerocoolservices.com | F4: Amateurish / DIY template | G4: 5 | H4: 43 | I4: Warm | J4: Carson Brender | K4: Generic template-builder site, awkward copy ("Speak With a Licensed Technician Licensed Now"), thin content, stock contact form | L4: Google Maps; WebSearch; direct site visit | M4: 2026-07-02 | N4: Y | O4: 2026-07-14 | P4: No answer — call again. Note: site has HouseCall Pro booking widget already active. | July 14 — voice agent again. Left inquiry about their HouseCall Pro booking feature. Told them best callback time is before 11am. | July 14 — spoke to Jeremy (staff). Got Rusty's personal cell (transcript garbled — Jose has it). Best time to call: after 12pm today.
A5: Arlington | B5: Anderson Mechanical Heating & Cooling INC. | C5: (425) 422-0160 | D5: No | E5: N/A | F5: N/A | G5: 4.9 | H5: 14 | I5: Watch | J5: Jesse Anderson (registered agent) | K5: No website found. Only 14 reviews so it doesn't yet clear the 30+ review bar - worth rechecking as it grows | L5: Google Maps; WebSearch | M5: 2026-07-02 | N5: N
A6: Arlington | B6: Frog HVAC LLC | C6: (425) 359-7988 | D6: Yes | E6: froghvac.com | F6: Warm - grammatical error in hero headline ("Based Of Arlington" instead of "Based In"), generic stock photo of unrelated modern architectural interior (not their own trucks/team), garish rainbow frog mascot clashing with green header/orange CTA scheme | G6: 4.6 | H6: 28 | I6: Warm | K6: 28 reviews clears the new 25+ bar. Site technically exists but actively hurts them - stock photography instead of real work, plus a copy error on the hero headline. Good "here's specifically what's broken" pitch. | L6: Google Maps | M6: 2026-07-02 | N6: N
A7: Marysville | B7: Montanos Heating & Cooling Services | C7: (425) 314-1814 | D7: Yes | E7: montanosheating.com | F7: Outdated / amateurish | G7: 5 | H7: 54 | I7: Warm | J7: Joel (last name not confirmed) | K7: Generic dark template, mismatched personal-vehicle stock photo, business email is a @gmail.com address, overlapping lead-gen popup blocks page content | L7: Google Maps; WebSearch; direct site visit | M7: 2026-07-02 | N7: Y | O7: 2026-07-14 | P7: July 14 — no answer, no voicemail.
A8: Marysville | B8: Kodiak Heating and Cooling | C8: (425) 883-4871 | D8: Yes | E8: kodiakheatingandcooling.com | F8: Dated / generic | G8: 5 | H8: 91 | I8: Warm | J8: Thomas Hager & Steven Hyde | K8: Uses generic stock family photo (not their own team or trucks), dated template layout | L8: Google Maps; WebSearch; direct site visit | M8: 2026-07-02 | N8: Y | O8: 2026-07-14 | P8: July 14 — Nicole (staff) answered. Thomas/Steven not in. Website was just revamped — skip website angle. Actually Washington Water Heaters (tankless specialist). Got Tom email: tanklesstom@gmail.com. Send booking pitch email.
A9: Stanwood | B9: Cool Heat 365 LLC | C9: (425) 740-4212 | D9: Yes | E9: coolheat365.com | F9: Amateurish / outdated | G9: 4.8 | H9: 367 | I9: Warm | J9: Rusty (last name not confirmed) | K9: Cartoon-style flame mascot logo, business email is a @yahoo.com address, broken icon placeholders next to contact info in header | L9: Google Maps; WebSearch; direct site visit | M9: 2026-07-02 | N9: Y | O9: 2026-07-14 | P9: July 14 — spoke to Jeremy (staff). Got Rusty's personal cell (transcript garbled — Jose has it). Best time to call: after 12pm today.
A10: Mount Vernon | B10: Handy's Heating | C10: (360) 428-0969 | D10: Yes | E10: handysheating.com | F10: Outdated | G10: 4.6 | H10: 260 | I10: Warm | K10: Dated embossed-text logo, homepage banner still promoting a stale seasonal ("holidays") tune-up offer, generic stock house photo | L10: Google Maps; WebSearch; direct site visit | M10: 2026-07-02 | N10: N
A11: Mount Vernon | B11: Nordic Temperature Control | C11: (360) 873-8163 | D11: Yes | E11: nordictempcontrol.com | F11: Cluttered / dated | G11: 4.9 | H11: 130 | I11: Warm | K11: Aggressive SMS sign-up popup on load, multiple stacked widgets (chat bubble, HomeAdvisor badge, cookie banner) creating cluttered UX | L11: Google Maps; WebSearch; direct site visit | M11: 2026-07-02 | N11: Y | O11: 2026-07-14 | P11: July 14 — screener answered, directed to email. Got contact email (transcript garbled — likely contact@nordictemperaturecontrol.com — verify). Send booking pitch email.
A12: Mount Vernon (Burlington) | B12: Alpine Heating and Cooling | C12: (360) 755-5146 | D12: Yes | E12: alpineheat.com | F12: Dated | G12: 4.7 | H12: 82 | I12: Warm | K12: Serviceable but dated site - lacks inline lead capture form and a modern visual refresh | L12: Google Maps; WebSearch | M12: 2026-07-02 | N12: N
A13: Everett | B13: AirPros Energy Heating and Cooling | C13: (425) 600-7540 | D13: Yes | E13: airprosenergy.com | F13: Amateurish | G13: 5 | H13: 139 | I13: Warm | J13: Richie & Mark (co-founders, 2007) | K13: No logo/branding in header, plain text-heavy layout, grammatical typo in hero copy ("take control your home comfort") | Has online booking feature on website already — warm lead, skip the booking education, go straight to website quality angle. | L13: Google Maps; WebSearch; direct site visit | M13: 2026-07-02 | N13: N | O13: 2026-07-14 | P13: July 14 — no answer, no voicemail. | July 14 — receptionist picked up (owner unavailable). Has online booking but SET TIMES only, not live availability. Got email: info@airprosenergy.com. Send follow-up email today.
A14: Everett | B14: Top Quality Home Service | C14: (425) 365-5589 | D14: No | E14: N/A | F14: N/A | G14: 5 | H14: 32 | I14: Hot | J14: Cody (last name not confirmed) | K14: No dedicated business website found despite a "Website" link on the Google listing; searches turn up only directory/aggregator pages, not an owned site | L14: Google Maps; WebSearch | M14: 2026-07-02 | N14: Y | O14: 2026-07-13 | P14: No answer — call again | Called back — panicked, posed as customer needing AC repair, bailed. Call back tomorrow, open by owning it.
A15: Everett | B15: Climate Pro LLC | C15: (425) 787-5804 | D15: Yes | E15: climatepronw.com | F15: Dated | G15: 4.6 | H15: 38 | I15: Warm | K15: Generic stock family photo, cluttered dated template, UI text-overlap glitch in hero banner | L15: Google Maps; WebSearch; direct site visit | M15: 2026-07-02 | N15: N
A16: Lake Stevens | B16: Arctic Heat LLC | C16: (360) 540-1920 | D16: No | E16: N/A | F16: N/A | G16: 5 | H16: 75 | I16: Hot | J16: Sergey & Natalia Nikolin | K16: No dedicated website found; only directory/social listings (Facebook, Yelp, BBB, Networx) turn up | L16: Google Maps; WebSearch | M16: 2026-07-02 | N16: Y | O16: 2026-07-08 | P16: Called — business closed. Sergey now works for different company. Dead lead.
A17: Lake Stevens | B17: Puget Heating Company | C17: (425) 334-4111 | D17: Yes | E17: pugetheating.com | F17: Very outdated | G17: 4.8 | H17: 37 | I17: Warm | K17: Established 1974; cloudy-sky gradient background, cartoon mechanic mascot, clip-art scalloped borders around product photos - classic mid-2000s design | L17: Google Maps; WebSearch; direct site visit | M17: 2026-07-02 | N17: N
A18: Lake Stevens | B18: Elevated Mechanical LLC | C18: (425) 530-7192 | D18: Yes | E18: elevatedmechanicalnw.com | F18: Amateurish / thin | G18: 5 | H18: 34 | I18: Warm | K18: Bare no-code template site - just a centered logo on a blank page, no hero content or CTA, business email is a @gmail.com address | L18: Google Maps; WebSearch; direct site visit | M18: 2026-07-02 | N18: N
A19: Snohomish | B19: McFarland Heating & Air | C19: (360) 568-4205 | D19: Yes | E19: mcfarlandhvac.com | F19: Broken / technical issues | G19: 5 | H19: 46 | I19: Hot | J19: Howard, Andy & Zack (family owners) | K19: Page title tag shows raw unescaped HTML code ("McFarland Heating & Air<br />360-568-4205") - a broken/badly coded site | L19: Google Maps; WebSearch | M19: 2026-07-02 | N19: Y | O19: 2026-07-14 | P19: VERBAL YES — Zach (co-owner) picked up. Said no twice, Jose pivoted with free case study offer. Zach: I dig that, send me a mock-up. Gave personal cell. Bonded over AI. Text demo link NOW.
A20: Snohomish | B20: Pilchuck Heating | C20: (425) 585-0659 | D20: Yes | E20: pilchuckheating.com | F20: Broken / buggy | G20: 4.3 | H20: 32 | I20: Warm | K20: Navigation bar renders duplicated and stacked on page load, large broken empty sections - clear front-end bugs | L20: Google Maps; WebSearch; direct site visit | M20: 2026-07-02 | N20: N
A21: Snohomish | B21: Snohomish Furnace & Air Conditioning | C21: (425) 610-6635 | D21: Yes | E21: snohomishfurnace.com | F21: Cluttered / stale | G21: 4.7 | H21: 168 | I21: Do Not Call | K21: Intrusive popup blocks content on load, homepage still promoting a stale "Spring Service" offer in July | L21: Google Maps; WebSearch; direct site visit | M21: 2026-07-02 | N21: Y | O21: 2026-07-14 | P21: July 14 — owner picked up. Spring sale opener landed but GoDaddy follow-up triggered ARE YOU SELLING ME SOMETHING. Hung up. Not interested.
A22: Lynnwood | B22: Lynnwood Heating LLC | C22: (206) 741-6980 | D22: Yes | E22: hvaclynnwood.com | F22: Unpolished | G22: 4.8 | H22: 155 | I22: Warm | K22: Large broken-looking blank white gap at top of homepage before content loads; business email is a @gmail.com address | L22: Google Maps; WebSearch; direct site visit | M22: 2026-07-02 | N22: N
A23: Monroe | B23: Genesis Heating, Cooling & Refrigeration | C23: (425) 261-9095 | D23: Yes | E23: genesishvacr.com | F23: Broken / technical issues | G23: 4.8 | H23: 73 | I23: Warm | K23: Broken icon font (tofu boxes) throughout nav/header, large blank empty section below nav where hero content should render | L23: Google Maps; WebSearch; direct site visit | M23: 2026-07-02 | N23: N
A24: Oak Harbor | B24: A&R HVAC LLC | C24: (360) 499-1829 | D24: Yes (not real site) | E24: anrhvac.com | F24: No real site - link-in-bio page | G24: 5 | H24: 67 | I24: Skip | K24: Domain just redirects to a bare "link in bio" style landing page (literal page title), not an actual business website. Business email is a @gmail.com address | L24: Google Maps; WebSearch; direct site visit | M24: 2026-07-02 | N24: N | P24: July 14 — already using Jobber for booking. Skip.
A25: Sedro-Woolley | B25: Right Way Plumbing & Heating | C25: (360) 855-2665 | D25: Yes | E25: rightwayplumb-heat.com | F25: Dated | G25: 4.2 | H25: 33 | I25: Warm | K25: Massively keyword-stuffed page title (SEO spam from an older era), western-saloon style drop-shadow serif font for headings, generic warehouse stock photo | L25: Google Maps; WebSearch; direct site visit | M25: 2026-07-02 | N25: N
A26: Sedro-Woolley | B26: Taxdahl Heating & Air Conditioning | C26: (360) 708-4675 | D26: Yes | E26: taxdahlheating.com | F26: Dated | G26: 4.9 | H26: 31 | I26: Warm | K26: Basic, outdated site design with no lead capture form or modern visual refresh | L26: Google Maps; WebSearch | M26: 2026-07-02 | N26: N
A27: Ferndale | B27: A Plus Heating and Air Conditioning | C27: (564) 209-4966 | D27: No | E27: facebook.com (no dedicated site) | F27: N/A | G27: 5 | H27: 33 | I27: Hot | J27: Vlad | K27: No real website - Maps/search only surfaces a Facebook page as their web presence. Owner Vlad confirmed via multiple reviews ("Vlad and his son were extremely professional...", "Vlad replaced our furnace..."). | L27: Google Maps; WebSearch | M27: 2026-07-02 | N27: Y | O27: 2026-07-14 | P27: Called x2 — no answer both times. Call again. | July 14 — no answer, no voicemail. 3rd attempt. Try before 8am.
A28: Port Orchard | B28: Simons Heating Cooling & Appliance Repair | C28: (253) 649-9922 | D28: Yes | E28: simonshvacrepair.com | F28: Warm - broken/thin site (huge blank white gaps below nav, testimonials section never loads), generic unbranded pill-button nav, no real hero/logo imagery, cheap "by Smartarget" 3rd-party widget badge, gmail contact | G28: 5 | H28: 37 | I28: Warm | K28: 3+ red flag signals: broken layout, no branding, cheap widget, gmail email (SIMONSHEATINGCOOLINGAPPLIANCE@GMAIL.COM) | L28: Google Maps; WebSearch | M28: 2026-07-02 | N28: N
A29: Ferndale | B29: Whatcom Heating and Air Conditioning LLC | C29: (360) 389-7583 | D29: Yes | E29: whatcomhvac.com | F29: Warm - severely underbuilt site: plain text-only header (no logo/branding), massive blank gray space below nav with zero hero content/CTA/headline, only a small Facebook icon link | G29: 5 | H29: 31 | I29: Warm | K29: Also serves Lynden - same business. Site is essentially non-functional as a marketing/lead-gen tool despite technically "having a website". | L29: Google Maps; WebSearch | M29: 2026-07-02 | N29: N
A30: Port Orchard | B30: Air Anderson Inc. | C30: (360) 674-7125 | D30: Yes | F30: Not assessed | G30: 4.2 | H30: 15 | I30: Watch | K30: Below 25+ review threshold - recheck later | L30: Google Maps | M30: 2026-07-02 | N30: N
A31: Port Orchard | B31: A & M Heating | C31: (360) 895-8580 | D31: No | E31: N/A | F31: N/A | G31: 4.5 | H31: 15 | I31: Watch | K31: No website shown on Maps; below 25+ review threshold - recheck later | L31: Google Maps | M31: 2026-07-02 | N31: N
A32: Poulsbo | B32: YJK Dryer vent & Air Duct Cleaning Services | C32: (360) 276-5825 | D32: No | E32: N/A | F32: N/A | G32: 4.6 | H32: 20 | I32: Watch | K32: Below 25+ review threshold; narrower duct-cleaning scope rather than full HVAC - recheck later | L32: Google Maps | M32: 2026-07-02 | N32: N
A33: Silverdale | B33: Brooks Comfort Zone LLC | C33: (360) 643-0539 | D33: Yes | F33: Not assessed | G33: 4.1 | H33: 23 | I33: Watch | K33: Below 25+ review threshold - recheck later | L33: Google Maps | M33: 2026-07-02 | N33: N
A34: Silverdale | B34: Mayda & Sons Mechanical | C34: (360) 692-9003 | D34: Yes | F34: Not assessed | G34: 4.7 | H34: 15 | I34: Watch | K34: Below 25+ review threshold - recheck later | L34: Google Maps | M34: 2026-07-02 | N34: N
A35: Ferndale | B35: Andy Refrigeration | C35: (360) 820-9801 | D35: Yes | F35: Not assessed | G35: 4.1 | H35: 12 | I35: Watch | K35: Below 25+ review threshold - recheck later | L35: Google Maps | M35: 2026-07-02 | N35: N
A36: Ferndale | B36: Mumm's LLC Heating & A/C contractor | C36: (360) 201-4822 | D36: Yes | F36: Not assessed | G36: 4.8 | H36: 12 | I36: Watch | K36: Below 25+ review threshold - recheck later | L36: Google Maps | M36: 2026-07-02 | N36: N
A37: Lynden | B37: Solera Hurley HVAC Contractor Lynden | C37: (253) 367-2447 | D37: No | E37: N/A | F37: N/A | G37: 5 | H37: 10 | I37: Watch | K37: No website shown on Maps; below 25+ review threshold. Name suggests possible franchise/rebrand - worth rechecking as it grows | L37: Google Maps | M37: 2026-07-02 | N37: N
A38: Lynden | B38: Reliance Indoor Air Quality Heating & Air Conditioning | C38: (360) 410-9159 | D38: Yes | F38: Not assessed | G38: 4.8 | H38: 16 | I38: Watch | K38: Below 25+ review threshold - recheck later | L38: Google Maps | M38: 2026-07-02 | N38: Y | O38: 2026-07-09 | P38: VERBAL YES — free case study. Justin on rooftop, said text him the link. Follow up with text NOW.
A39: Yelm | B39: Manus Mechanical | C39: (253) 248-5925 | D39: No | E39: N/A | F39: No website - Maps shows "Add website" prompt | G39: 5 | H39: 26 | I39: Hot | J39: Alex Manus | K39: No website at all, confirmed via Maps "Add missing information" prompt. Owner name confirmed via reviews. | L39: Google Maps | M39: 2026-07-02 | N39: Y | O39: 2026-07-09 | P39: Called x2 + callback — not interested. Do not call again.
A40: Yelm | B40: Ed's Heating and Cooling LLC | C40: (253) 753-8177 | D40: Yes (dead) | E40: edsheatingandcoolingwa.com | F40: Domain dead - "Domain not found"/privacy error on https and http | G40: 5 | H40: 231 | I40: Hot | K40: Best find of Round 6 - 231 reviews, 5.0 stars, but domain completely dead on both https and http. | L40: Google Maps | M40: 2026-07-02 | N40: Y | O40: 2026-07-14 | P40: Called x2 — voicemail both times. Left voicemail on 2nd attempt. Call again Day 5. | July 14 — 3rd attempt, voicemail left. Said: tried a couple times, have a system to capture missed calls so they don't lose prospects. Left callback #.
A41: Yelm | B41: A'ALONA HVAC SOLUTIONS LLC | C41: (866) 332-0926 | D41: Unknown | F41: Not assessed | G41: 5 | H41: 5 | I41: Watch | K41: Below 25+ review threshold - recheck later. | L41: Google Maps | M41: 2026-07-02 | N41: N
A42: Yelm | B42: A'alona HVAC Solutions | C42: (206) 375-2851 | D42: Unknown | F42: Not assessed | G42: 5 | H42: 8 | I42: Watch | K42: Below 25+ review threshold - possible second location of same brand as above. Recheck later. | L42: Google Maps | M42: 2026-07-02 | N42: N
A43: Orting | B43: Washington HVAC Heating Service | C43: (360) 323-1444 | D43: No | E43: N/A | F43: No website shown on Maps | G43: 5 | H43: 4 | I43: Watch | K43: Genuinely Orting-based (134 Washington Ave SE), no website, but below 25+ threshold. Recheck later. | L43: Google Maps | M43: 2026-07-02 | N43: N
A44: Eatonville | B44: Glacier Peak Mechanical LLC | C44: (253) 228-0009 | D44: Unknown | F44: Not assessed | G44: 5 | H44: 17 | I44: Watch | K44: Below 25+ review threshold - recheck later. | L44: Google Maps | M44: 2026-07-02 | N44: N
A45: Buckley | B45: Proaire Heating & Cooling Corp | C45: (253) 225-2586 | D45: Unknown | F45: Not assessed | G45: 4.4 | H45: 9 | I45: Watch | K45: Below 25+ review threshold - recheck later. | L45: Google Maps | M45: 2026-07-02 | N45: N
A46: Port Angeles | B46: Dave's Heating & Cooling Service, Inc. | C46: (360) 452-0939 | D46: Yes (broken) | E46: davesheatingpa.com | F46: Broken/missing hero image (large black void) + duplicated boilerplate copy reused verbatim across sections | G46: 5 | H46: 33 | I46: Warm | J46: Paul Todd Reed (L&I principal) | K46: 2 red-flag signals per Step 4 checklist. | L46: Google Maps | M46: 2026-07-02 | N46: N
A47: Port Angeles | B47: Strait Comfort Systems | C47: (360) 565-5191 | D47: Unknown | F47: Not assessed | G47: 5 | H47: 19 | I47: Watch | K47: Below 25+ review threshold - recheck later. | L47: Google Maps | M47: 2026-07-02 | N47: N
A48: Port Angeles | B48: Nice Guy Heating and Air | C48: (360) 775-6625 | D48: Unknown | F48: Not assessed | G48: 5 | H48: 15 | I48: Watch | K48: Below 25+ review threshold - recheck later. | L48: Google Maps | M48: 2026-07-02 | N48: N
A49: Sequim | B49: Knight Heating and Cooling | C49: (360) 797-4505 | D49: No | E49: N/A | F49: No website - Maps shows "Add website" prompt | G49: 4.7 | H49: 37 | I49: Dead | K49: No website at all, confirmed via Maps "Add missing information" prompt. One negative review re: thermostat dispute but overall rating still clears bar. | L49: Google Maps | M49: 2026-07-02 | N49: Y | O49: 2026-07-14 | P49: July 14 — number disconnected/changed. Dead lead.
A50: Everson | B50: Aeon Mechanical LLC | D50: Unknown | F50: Not assessed | G50: 5 | H50: 19 | I50: Watch | K50: Below 25+ review threshold; category listed as general "Contractor" not confirmed HVAC-specific - verify category before treating as live lead. | L50: Google Maps | M50: 2026-07-02 | N50: N
A51: Aberdeen | B51: ShoresAir | C51: (360) 590-0215 | D51: No | E51: N/A | F51: No website - Maps shows "Add website" prompt | G51: 5 | H51: 33 | I51: Do Not Call | J51: Chris | K51: No website at all, confirmed via Maps "Add missing information" prompt. Women-owned business. Owner name Chris confirmed via multiple reviews. | L51: Google Maps | M51: 2026-07-02 | N51: Y | O51: 2026-07-13 | P51: No answer — call again | Called back — not interested. DO NOT CALL.
A52: Aberdeen | B52: Robbins Air Inc | C52: (360) 538-7003 | D52: Yes (dated) | E52: robbinsairinc.com | F52: Dated 2010s-era template: generic stock photography (commercial condenser units, not their own trucks/team), tan/beige beveled-button design cues, unclear/broken "Email" form field | G52: 4.6 | H52: 116 | I52: Warm | J52: Carl W Robbins (L&I principal) | K52: 2+ red-flag signals per Step 4 checklist. | L52: Google Maps | M52: 2026-07-02 | N52: N
A53: Montesano | B53: HANSON HEATING & COOLING | C53: (360) 470-3993 | D53: Unknown | F53: Not assessed | G53: 5 | H53: 8 | I53: Watch | K53: Below 25+ review threshold - recheck later. | L53: Google Maps | M53: 2026-07-02 | N53: N
A54: Montesano | B54: Evergreen Air | C54: (360) 209-4379 | D54: Unknown | F54: Not assessed | G54: 5 | H54: 7 | I54: Watch | K54: Below 25+ review threshold - recheck later. | L54: Google Maps | M54: 2026-07-02 | N54: N
A55: Hoquiam | B55: Air Heads Heating & Cooling, LLC | D55: Unknown | F55: Not assessed | G55: 4 | H55: 12 | I55: Watch | K55: Below 25+ review threshold - recheck later. | L55: Google Maps | M55: 2026-07-02 | N55: N
A56: Chehalis | B56: Mills Northwest Heating & Cooling Inc | C56: (360) 748-7961 | D56: No | E56: N/A | F56: No website - Maps shows "Add website" prompt | G56: 4.4 | H56: 27 | I56: Hot | K56: No website at all, confirmed via Maps "Add missing information" prompt. One negative review re: prior redo work but overall rating still clears bar. | L56: Google Maps | M56: 2026-07-02 | N56: N
A57: Chehalis | B57: Advanced Energy Systems Inc. | C57: (360) 207-1419 | D57: Yes | F57: Not assessed | G57: 4.8 | H57: 21 | I57: Watch | K57: Below 25+ review threshold - recheck later. | L57: Google Maps | M57: 2026-07-02 | N57: N
A58: Chehalis | B58: Mohoric Refrigeration | C58: (360) 736-9969 | D58: Yes | F58: Not assessed | G58: 4.5 | H58: 8 | I58: Watch | K58: Below 25+ review threshold - recheck later. | L58: Google Maps | M58: 2026-07-02 | N58: N
A59: Tumwater | B59: Community Heating and Cooling LLC | C59: (360) 923-4229 | D59: No | E59: N/A | F59: No website - Maps shows "Add website" prompt | G59: 4.8 | H59: 79 | I59: Hot | K59: No website at all, confirmed via Maps "Add missing information" prompt. 79 reviews is one of the strongest review bases of any Hot find in the project. Found in Tumwater despite Thurston County looking saturated at first glance - proves individual verification is still worth it even in nominally saturated markets. | L59: Google Maps | M59: 2026-07-02 | N59: Y | O59: 2026-07-14 | P59: July 14 — line busy, auto-disconnected. Try again another time.
A60: Tumwater | B60: Quality Heating & Air, LLC | C60: (360) 742-6323 | D60: Yes (hijacked) | E60: qualityheatingllc.com | F60: Domain expired and now redirects to an unrelated Thai online lottery/gambling site - not a working business site by any definition | G60: 4.8 | H60: 55 | I60: Hot | J60: Justin | K60: Best/most unusual find of Round 7 - their old domain now serves gambling content. Owner name Justin confirmed via multiple reviews. | L60: Google Maps | M60: 2026-07-02 | N60: Y | O60: 2026-07-14 | P60: VERBAL YES — free case study. Justin on rooftop, said text him the link. Follow up with text NOW. | Follow-up call — still interested. Busy but asked Jose to call back at 2pm TODAY. 2pm call scheduled.
A61: Lacey | B61: All-Star Heating & Cooling | C61: (360) 522-7284 | D61: No | E61: N/A | F61: No website - Maps shows "Add website" prompt | G61: 5 | H61: 84 | I61: Hot | J61: Alex | K61: No website at all, confirmed via Maps "Add missing information" prompt. Owner name Alex confirmed via review ("Alex, the owner and lead engineer"). | L61: Google Maps | M61: 2026-07-02 | N61: Y | O61: 2026-07-10 | P61: Called x2 — not interested. "Small business, don't need service." Folded too early. Dead.
A62: Tumwater | B62: Custom Comfort Northwest Heating and Cooling | D62: Unknown | F62: Not assessed | G62: 4.5 | H62: 8 | I62: Watch | K62: Below 25+ review threshold - recheck later. | L62: Google Maps | M62: 2026-07-02 | N62: N
A63: Yelm | B63: Paul's Custom Heating & A/C INC. | D63: Unknown | F63: Not assessed | G63: 4.9 | H63: 21 | I63: Watch | K63: Surfaced via "People also search for" on Ed's Heating and Cooling LLC page - below 25+ review threshold, recheck later. | L63: Google Maps | M63: 2026-07-02 | N63: N
A64: Deming | B64: Heating Guy Inc | C64: (360) 927-4643 | D64: No | E64: N/A | F64: No website - Maps shows Add website prompt | G64: 5 | H64: 8 | I64: Hot | J64: Lawrence (Larry) Duncan | K64: EXPERIMENTAL FLAG - only 8 Google reviews (below standard 25+ bar) but WA L&I license HEATIGI947D4 (HVAC/RFRG specialty) has been continuously ACTIVE since 03/24/2006 - 19 years - discovered via L&I name-search cross-reference, missed by every Google Maps query run for Deming/Concrete/Everson/Nooksack in Round 6. Promoted to Hot on the theory that a 19-year active license is at least as strong a legitimacy signal as 25 reviews, especially in a town this small. Flagging for your judgment as the first test case of this alternate criteria - review before calling. | L64: WA L&I contractor search + Google Maps | M64: 2026-07-02
A65: Raymond | B65: A R Heating & Cooling | C65: (360) 999-0928 | D65: Unknown | F65: Not assessed | G65: 5 | H65: 8 | I65: Watch | K65: Below 25+ review threshold - recheck later. Part of population-floor experiment (Pacific County) - Raymond otherwise returned only duplicates of already-logged Grays Harbor businesses and category mismatches. | L65: Google Maps | M65: 2026-07-02 | N65: N
A66: Long Beach | B66: Bachers Heating & Cooling LLC. | C66: (360) 214-9966 | D66: Yes | E66: bachers-heating.com | F66: Not individually site-verified - real domain exists, owner CJ confirmed via reviews | G66: 4.8 | H66: 24 | I66: Watch | J66: CJ | K66: 1 review short of the 25+ bar. One sharply negative review (missed follow-up) alongside otherwise strong reviews - worth a second look when it crosses threshold. Part of population-floor experiment (Pacific County/Long Beach Peninsula, population ~1,400) - smallest town with any independent HVAC presence found in the whole project so far. | L66: Google Maps | M66: 2026-07-02 | N66: N
A67: Enumclaw | B67: Lloyd's Heating & Sheet Metal | C67: (360) 825-2241 | D67: No | E67: N/A | G67: 5 | H67: 10 | I67: Hot | J67: Dallas Jester Schenk | K67: L&I EXCEPTION APPLIED (2nd use, strongest yet): only 10 reviews but WA L&I HVAC/R license LLOYDHS101MT continuously active since 07/30/1990 (36 yrs), bonded + insured, zero violations. Maps listing UNCLAIMED with 'Add website' prompt = definitively no website. 5.0 reviews spanning 8+ yrs. Owner Dallas Schenk named in both reviews and L&I principals. 410 Roosevelt Ave E, Enumclaw. | L67: Google Maps + WA L&I verify | M67: 2026-07-02
A68: Elma | B68: PNW Heating And Cooling | D68: No | E68: N/A | F68: Not assessed | G68: 5 | H68: 11 | I68: Watch | J68: David | K68: No website AND no phone number on Maps ('Add website' + 'Add phone number' prompts both present). Owner David per review text. Reviews 2-4 years old, all 5.0. Contact info gap - pull phone from L&I/Facebook before any outreach. | L68: Google Maps | M68: 2026-07-02
A69: Ellensburg | B69: Brad & Burke Heating & AC | C69: (509) 962-9871 | D69: Yes | E69: bradandburke.com | F69: Poor | G69: 4.4 | H69: 48 | I69: Warm | K69: 3 red flags: generic stock-photo hero (not their team), huge blank/unrendered content sections mid-page, no lead-capture form (only a 'Get in touch!' text link). Long-established local name. 604 W University Way. | L69: Google Maps | M69: 2026-07-02
A70: Cle Elum | B70: Loveridge Mechanical & Sons LLC | C70: (509) 304-2368 | D70: Yes | E70: loveridgemech.com | F70: Poor | G70: 4.6 | H70: 26 | I70: Warm | K70: Family-owned, boilers/hydronic specialty. Red flags: no lead-capture form anywhere; 'Call Us Today' header with no number next to it; fire-pit section copy literally references 'Washington Boilers' (boilerplate pasted from another company's site); TWO duplicate GMB listings (one with 0 reviews) = digital neglect. Serves Cle Elum/Ellensburg/Kittitas + greater Seattle. | L70: Google Maps | M70: 2026-07-02
A71: Cle Elum | B71: Head Mechanical, Inc | C71: (206) 730-5178 | D71: Yes | F71: Not assessed | G71: 4.6 | H71: 9 | I71: Watch | K71: Under 25 reviews. Has website + online booking. Recheck as it grows. | L71: Google Maps | M71: 2026-07-02
A72: Wenatchee | B72: Wenatchee Heating & Cooling | C72: (509) 433-9025 | D72: Yes | E72: wenatcheeheatingandcooling.com | F72: Broken | G72: 5 | H72: 159 | I72: Warm | K72: CAVEAT - RE-VERIFY BEFORE CALLING: site rendered a completely blank white page with zero text content on two separate loads (may be a broken JS-only build). If confirmed broken, this is a top-tier Warm: 5.0 stars, 159 reviews, 24hr, and a dead-on-arrival website. No street address on Maps (service-area business). | L72: Google Maps | M72: 2026-07-02
A73: East Wenatchee | B73: Comfort Zone Heating & AC | F73: Not assessed | G73: 4.8 | H73: 6 | I73: Watch | K73: Under 25 reviews (PASF via Xtreme). Recheck later. | L73: PASF via Xtreme place page | M73: 2026-07-02
A74: Wenatchee | B74: Premier Heating & Cooling, LLC | C74: (509) 669-8010 | D74: Yes | E74: premierheatingandcoolingllc.com | F74: Broken / blurred | G74: 5 | H74: 81 | I74: Warm | J74: Pedro | K74: Hero image AND logo are permanently-blurred lazy-load placeholders that never resolve. GMB owner post is PAINTING-company boilerplate ('meticulous surface preparation, clean lines, color consultation') pasted into an HVAC listing - same wrong-vertical neglect pattern as Loveridge. No street address on Maps (service-area). Owner Pedro per reviews. 5.0 x 81 = strong pitch target. | L74: Google Maps | M74: 2026-07-02
A75: East Wenatchee | B75: Dick's Heating & Air Conditioning | C75: (509) 884-6444 | D75: Yes | E75: dicksheatingwenatchee.com | F75: Dated | G75: 4.6 | H75: 138 | I75: Warm | K75: Borderline Warm (2 flags): business email is dicksheating@hotmail.com (not even gmail), dated template with low-res pixelated hero. Counterpoint: owner responds to reviews thoughtfully - digitally present, just web-neglected. 5533 Nelpar Dr. | L75: Google Maps | M75: 2026-07-02
A76: Sunnyside | B76: Bos Refrigeration - Heating and Air Conditioning | C76: (509) 839-3466 | D76: Yes | F76: Not assessed | G76: 4.6 | H76: 12 | I76: Watch | J76: Mary J Bos (L&I principal) | K76: Under 25 reviews. Local Sunnyside address (3940 Alexander Rd). Recheck as it grows. | L76: Google Maps | M76: 2026-07-02
A77: Zillah | B77: TNG Heating & Air Conditioning, LLC | C77: (509) 865-3707 | D77: Yes | F77: Not assessed | G77: 4.8 | H77: 24 | I77: Watch | K77: ONE review shy of the 25 bar - recheck within weeks, not months. 1001 Vintage Valley Pkwy (surfaced under Toppenish search). | L77: Google Maps | M77: 2026-07-02
A78: Yakima (area) | B78: ASAP Heating & Cooling | C78: (509) 654-4335 | D78: Yes | F78: Not assessed | G78: 5 | H78: 20 | I78: Watch | K78: Under 25 reviews, no address shown (service-area). Recheck. | L78: Google Maps | M78: 2026-07-02
A79: East Wenatchee | B79: Cozy Comfort | F79: Not assessed | G79: 4.5 | H79: 8 | I79: Watch | K79: Under 25 reviews (PASF via Climatek/Jay's). Recheck. | L79: PASF | M79: 2026-07-02
A80: Bonney Lake | B80: House of Heat Inc | C80: (253) 862-9699 | D80: No | E80: N/A | H80: 0 | I80: Hot | J80: Phil G Baker (L&I principal) | K80: L&I GOLDMINE FIND: HVAC license active 45.5 YEARS (since 1981-01-06), still active today - and ZERO Google presence (no GMB listing at all, search redirects to other businesses). The purest ProBook profile possible. CAVEAT: no reviews anywhere means quality/operating status unverified - confirm they're still actively taking residential work when calling. Phone from L&I record. | L80: WA L&I bulk dataset | M80: 2026-07-02
A81: Carnation | B81: Action Heating & Air Conditioning | C81: (425) 788-0985 | D81: Yes | E81: actionhac.com | F81: Unverified | G81: 5 | H81: 6 | I81: Watch | J81: Bob | K81: L&I GOLDMINE FIND: license active 43 YEARS (since 1983). 5.0 x 6 reviews spanning 8 years, owner/operator Bob, one-man shop per reviews. Has a domain (actionhac.com) that could not be auto-verified - CHECK MANUALLY before flagging Hot/Warm. Serves Carnation/Duvall area, 24hr. | L81: WA L&I bulk dataset + Maps | M81: 2026-07-02
A82: Snohomish | B82: Monroe Heating & Refrigeration | C82: (360) 794-7914 | D82: No | E82: N/A | H82: 0 | I82: Hot | J82: Russell P Stendera (L&I principal) | K82: L&I GOLDMINE FIND: license active 41 YEARS (since 1985-05-07), still active - ZERO Google presence (no GMB listing). Same profile as House of Heat. Verify operating status by phone. Phone from L&I record. | L82: WA L&I bulk dataset | M82: 2026-07-02
A83: Snohomish | B83: Sammamish Heating & Cooling | C83: (360) 668-4902 | D83: No | E83: N/A | G83: 5 | H83: 1 | I83: Hot | J83: Perry Cook | K83: L&I GOLDMINE FIND: license active 32.7 YEARS (since 1993). UNCLAIMED Maps listing with 'Add website' prompt. Single review (from a Realtor, 6 yrs ago): 'I've had Perry Cook... service our furnaces for over 15 years... I recommend him to all of my clients.' Owner: Perry Cook. Zero web presence, decades of trade reputation. | L83: WA L&I bulk dataset + Maps | M83: 2026-07-02
A84: Nine Mile Falls | B84: L & K Heating | C84: (509) 768-5601 | D84: No | E84: N/A | H84: 0 | I84: Hot | J84: Larry Gene Lavalle (L&I principal) | K84: L&I GOLDMINE: license active 45.3 YEARS (since 1981-03-19). ZERO Google presence - the only Maps match for the name is an unrelated Texas company (254 area code, landkhvac.com). Spokane-area. Verify operating status when calling; phone from L&I record. | L84: WA L&I bulk dataset | M84: 2026-07-02
A85: Suquamish | B85: Todd Sheet Metal | C85: (360) 598-4517 | D85: No | E85: N/A | G85: 5 | H85: 2 | I85: Hot | J85: Gary | K85: L&I GOLDMINE: license active 45 YEARS (since 1981-07-01). UNCLAIMED Maps listing, 'Add website' prompt, no hours listed. 2 reviews confirm active HVAC work ('installed my new 5 ton heat pump and air handler', 8 months ago) and owner name Gary. Kitsap Peninsula. | L85: WA L&I bulk dataset + Maps | M85: 2026-07-02
A86: Issaquah | B86: P P S Heating & A/C Inc | C86: (425) 747-2841 | D86: No | E86: N/A | H86: 0 | I86: Hot | J86: Penny Ann Aske (L&I principal) | K86: L&I GOLDMINE: license active 39.3 YEARS (since 1987-03-01). ZERO Google presence - no GMB listing under any name variant. Eastside metro location. Verify operating status when calling; phone from L&I record. | L86: WA L&I bulk dataset | M86: 2026-07-02
A87: Spokane | B87: Tim's Comfort Plus | C87: (509) 534-6558 | D87: No | E87: N/A | H87: 0 | I87: Hot | J87: Tim | K87: L&I GOLDMINE: license active 35.1 YEARS (since 1991-05-17). No GMB under its own name. NOTE: a 'Sam's Heating & Cooling Comfort Plus' (4.7/15) exists in Spokane and a review there says 'Tim is awesome' - possibly related/renamed; clarify on the call. Phone from L&I record. | L87: WA L&I bulk dataset | M87: 2026-07-02
A88: Yakima | B88: Salazar Specialized Services | C88: (509) 457-7176 | D88: No | E88: N/A | H88: 0 | I88: Hot | K88: L&I GOLDMINE: license active 34.5 YEARS (since 1991-12-23). ZERO Google presence. Yakima - pairs with the confirmed-saturated Yakima core where an invisible old-timer is losing everything to Vance/Campbell. Phone from L&I record. | L88: WA L&I bulk dataset | M88: 2026-07-02
A89: Spokane Valley | B89: B & C Heating & Air Conditioning | C89: (509) 927-8861 | D89: No | E89: N/A | G89: 4.9 | H89: 7 | I89: Hot | J89: Bill | K89: L&I GOLDMINE: license active 33.9 YEARS (since 1992-07-23). Maps listing has 'Add website' + 'Add hours' prompts = no website, minimal listing management. 4.9 stars, owner Bill praised by name across reviews spanning 8 years. 14412 E Cataldo Ave, Spokane Valley. | L89: WA L&I bulk dataset + Maps | M89: 2026-07-02
A90: Port Orchard | B90: CJ's Quality Air Systems Inc | C90: (253) 857-5220 | D90: Yes | E90: cjsqualityairsystems.com | F90: Unverified | G90: 4.9 | H90: 15 | I90: Watch | J90: Curtis W Jackson (L&I principal) | K90: L&I GOLDMINE: license active 32.7 YEARS (since 1993-11-03). Qualifies via L&I longevity path. Family-owned, 4.9 x 15. Site exists but NOT yet quality-checked - verify cjsqualityairsystems.com next session, could upgrade to Warm or resolve to Skip. | L90: WA L&I bulk dataset + Maps | M90: 2026-07-02
A91: Yakima | B91: Eaton's Refrigeration | C91: (509) 575-6340 | D91: No | E91: N/A | H91: 0 | I91: Hot | J91: Brian K Eaton (L&I principal) | K91: L&I GOLDMINE: license active 32 YEARS (since 1994-07-01, and holds a second license from 2000). ZERO Google presence - no GMB under its name. Refrigeration/HVAC in the saturated Yakima core where invisibility is fatal. Phone from L&I record. | L91: WA L&I bulk dataset | M91: 2026-07-02
A92: Renton | B92: Complete Heating & A/C | C92: (253) 867-1000 | D92: No | E92: N/A | I92: Hot | K92: LEGACY IMPORT from old hvac-prospects.xlsx (pre-Round-9 0-5 scoring) - re-verify current status before calling. No website found — 35+ year old company running entirely on referrals | L92: Legacy tracker | M92: 2026-07-02
A93: Walla Walla | B93: Young's Heating and Cooling | C93: (509) 525-4328 | D93: No | E93: N/A | I93: Hot | K93: LEGACY IMPORT from old hvac-prospects.xlsx (pre-Round-9 0-5 scoring) - re-verify current status before calling. No website found — small owner-operated shop in Walla Walla | L93: Legacy tracker | M93: 2026-07-02
A94: Walla Walla | B94: American Air Heating & Cooling | C94: (509) 529-0800 | D94: No | E94: N/A | I94: Hot | K94: LEGACY IMPORT from old hvac-prospects.xlsx (pre-Round-9 0-5 scoring) - re-verify current status before calling. No website found — Walla Walla local operator, directory listing only | L94: Legacy tracker | M94: 2026-07-02
A95: Spokane | B95: HVAC 1 Pros | C95: (509) 218-1716 | D95: Yes | E95: hvac1pros.com | F95: Legacy score 1/5 | I95: Warm | K95: LEGACY IMPORT from old hvac-prospects.xlsx (pre-Round-9 0-5 scoring) - re-verify current status before calling. One-page site with no lead form, no reviews, stock-photo only design | L95: Legacy tracker | M95: 2026-07-02
A96: Kennewick | B96: Bob Rhodes Heating & AC | C96: (509) 783-3291 | D96: Yes | E96: bobrhodesheatingandac.com | F96: Legacy score 2/5 | I96: Warm | K96: LEGACY IMPORT from old hvac-prospects.xlsx (pre-Round-9 0-5 scoring) - re-verify current status before calling. Very old CMS template, no lead form, no reviews displayed on homepage ALSO ON L&I GOLDMINE (license since 2000-07-17). | L96: Legacy tracker | M96: 2026-07-02
A97: Spokane | B97: Air Design | D97: Yes | E97: airdesignspokane.com | F97: Legacy score 2/5 | I97: Warm | K97: LEGACY IMPORT from old hvac-prospects.xlsx (pre-Round-9 0-5 scoring) - re-verify current status before calling. In business since 1979; dated site with no lead form or social proof | L97: Legacy tracker | M97: 2026-07-02
A98: Lynnwood | B98: Nortech Heating & Refrigeration | C98: (425) 775-0808 | D98: Yes | E98: nortechservices.com | F98: Legacy score 2/5 | I98: Warm | K98: LEGACY IMPORT from old hvac-prospects.xlsx (pre-Round-9 0-5 scoring) - re-verify current status before calling. Commercial-heavy site with poor residential lead capture and old design | L98: Legacy tracker | M98: 2026-07-02
A99: Spokane | B99: Evergreen Heating & Cooling | C99: (509) 534-8305 | D99: Yes | E99: evergreenheatcool.com | F99: Legacy score 2/5 | I99: Warm | K99: LEGACY IMPORT from old hvac-prospects.xlsx (pre-Round-9 0-5 scoring) - re-verify current status before calling. Long-running Spokane company with outdated site, no lead form or reviews ALSO ON L&I GOLDMINE (license since 2005-10-12). | L99: Legacy tracker | M99: 2026-07-02
A100: Tacoma | B100: Above the Best Heating & Air | D100: Yes | E100: abovethebesthvac.com | F100: Legacy score 2/5 | I100: Warm | K100: LEGACY IMPORT from old hvac-prospects.xlsx (pre-Round-9 0-5 scoring) - re-verify current status before calling. Small operator, basic template site with no lead form or social proof ALSO ON L&I GOLDMINE (license since 2008-05-12). | L100: Legacy tracker | M100: 2026-07-02
...

Sheet Summary
A1: Metric | B1: Count
A2: Total businesses logged | B2: =COUNTA(Prospects!B2:B1000)+COUNTA('Skipped (Reference)'!B2:B1000)
A3: Hot (no website, 4+ stars, 25+ reviews) | B3: =COUNTIF(Prospects!I2:I1000,"Hot")
A4: Warm (bad/broken website, 4+ stars, 25+ reviews) | B4: =COUNTIF(Prospects!I2:I1000,"Warm")
A5: Watch (close but under review threshold) | B5: =COUNTIF(Prospects!I2:I1000,"Watch")
A6: Skip (moved to reference tab) | B6: =COUNTA('Skipped (Reference)'!B2:B1000)
A7: Arlington businesses logged | B7: =COUNTIF(Prospects!A2:A1000,"Arlington")+COUNTIF('Skipped (Reference)'!A2:A1000,"Arlington")
A8: Marysville businesses logged | B8: =COUNTIF(Prospects!A2:A1000,"Marysville")+COUNTIF('Skipped (Reference)'!A2:A1000,"Marysville")
A9: Stanwood businesses logged | B9: =COUNTIF(Prospects!A2:A1000,"Stanwood")+COUNTIF('Skipped (Reference)'!A2:A1000,"Stanwood")
A10: Mount Vernon businesses logged | B10: =COUNTIF(Prospects!A2:A1000,"Mount Vernon")+COUNTIF('Skipped (Reference)'!A2:A1000,"Mount Vernon")
A11: Everett businesses logged | B11: =COUNTIF(Prospects!A2:A1000,"Everett")+COUNTIF('Skipped (Reference)'!A2:A1000,"Everett")
A12: Lake Stevens businesses logged | B12: =COUNTIF(Prospects!A2:A1000,"Lake Stevens")+COUNTIF('Skipped (Reference)'!A2:A1000,"Lake Stevens")
A13: Snohomish businesses logged | B13: =COUNTIF(Prospects!A2:A1000,"Snohomish")+COUNTIF('Skipped (Reference)'!A2:A1000,"Snohomish")
A14: Lynnwood businesses logged | B14: =COUNTIF(Prospects!A2:A1000,"Lynnwood")+COUNTIF('Skipped (Reference)'!A2:A1000,"Lynnwood")
A15: Edmonds businesses logged | B15: =COUNTIF(Prospects!A2:A1000,"Edmonds")+COUNTIF('Skipped (Reference)'!A2:A1000,"Edmonds")
A16: Monroe businesses logged | B16: =COUNTIF(Prospects!A2:A1000,"Monroe")+COUNTIF('Skipped (Reference)'!A2:A1000,"Monroe")
A17: Sedro-Woolley businesses logged | B17: =COUNTIF(Prospects!A2:A1000,"Sedro-Woolley")+COUNTIF('Skipped (Reference)'!A2:A1000,"Sedro-Woolley")
A18: Oak Harbor businesses logged | B18: =COUNTIF(Prospects!A2:A1000,"Oak Harbor")+COUNTIF('Skipped (Reference)'!A2:A1000,"Oak Harbor")
A19: Sultan businesses logged | B19: =COUNTIF(Prospects!A2:A1000,"Sultan")+COUNTIF('Skipped (Reference)'!A2:A1000,"Sultan")
A20: Camano Island businesses logged | B20: =COUNTIF(Prospects!A2:A1000,"Camano Island")+COUNTIF('Skipped (Reference)'!A2:A1000,"Camano Island")
A21: Anacortes businesses logged | B21: =COUNTIF(Prospects!A2:A1000,"Anacortes")+COUNTIF('Skipped (Reference)'!A2:A1000,"Anacortes")
A22: Mukilteo businesses logged | B22: =COUNTIF(Prospects!A2:A1000,"Mukilteo")+COUNTIF('Skipped (Reference)'!A2:A1000,"Mukilteo")
A23: Bellingham businesses logged | B23: =COUNTIF(Prospects!A2:A1000,"Bellingham")+COUNTIF('Skipped (Reference)'!A2:A1000,"Bellingham")
A24: Bremerton businesses logged | B24: =COUNTIF(Prospects!A2:A1000,"Bremerton")+COUNTIF('Skipped (Reference)'!A2:A1000,"Bremerton")
A25: Port Orchard businesses logged | B25: =COUNTIF(Prospects!A2:A1000,"Port Orchard")+COUNTIF('Skipped (Reference)'!A2:A1000,"Port Orchard")
A26: Poulsbo businesses logged | B26: =COUNTIF(Prospects!A2:A1000,"Poulsbo")+COUNTIF('Skipped (Reference)'!A2:A1000,"Poulsbo")
A27: Silverdale businesses logged | B27: =COUNTIF(Prospects!A2:A1000,"Silverdale")+COUNTIF('Skipped (Reference)'!A2:A1000,"Silverdale")
A28: Ferndale businesses logged | B28: =COUNTIF(Prospects!A2:A1000,"Ferndale")+COUNTIF('Skipped (Reference)'!A2:A1000,"Ferndale")
A29: Lynden businesses logged | B29: =COUNTIF(Prospects!A2:A1000,"Lynden")+COUNTIF('Skipped (Reference)'!A2:A1000,"Lynden")
A30: Blaine businesses logged | B30: =COUNTIF(Prospects!A2:A1000,"Blaine")+COUNTIF('Skipped (Reference)'!A2:A1000,"Blaine")
A31: Puyallup businesses logged | B31: =COUNTIF(Prospects!A2:A1000,"Puyallup")+COUNTIF('Skipped (Reference)'!A2:A1000,"Puyallup")
A32: Yelm businesses logged | B32: =COUNTIF(Prospects!A2:A1000,"Yelm")+COUNTIF('Skipped (Reference)'!A2:A1000,"Yelm")
A33: Orting businesses logged | B33: =COUNTIF(Prospects!A2:A1000,"Orting")+COUNTIF('Skipped (Reference)'!A2:A1000,"Orting")
A34: Eatonville businesses logged | B34: =COUNTIF(Prospects!A2:A1000,"Eatonville")+COUNTIF('Skipped (Reference)'!A2:A1000,"Eatonville")
A35: Buckley businesses logged | B35: =COUNTIF(Prospects!A2:A1000,"Buckley")+COUNTIF('Skipped (Reference)'!A2:A1000,"Buckley")
A36: Port Angeles businesses logged | B36: =COUNTIF(Prospects!A2:A1000,"Port Angeles")+COUNTIF('Skipped (Reference)'!A2:A1000,"Port Angeles")
A37: Sequim businesses logged | B37: =COUNTIF(Prospects!A2:A1000,"Sequim")+COUNTIF('Skipped (Reference)'!A2:A1000,"Sequim")
A38: Port Townsend businesses logged | B38: =COUNTIF(Prospects!A2:A1000,"Port Townsend")+COUNTIF('Skipped (Reference)'!A2:A1000,"Port Townsend")
A39: Everson businesses logged | B39: =COUNTIF(Prospects!A2:A1000,"Everson")+COUNTIF('Skipped (Reference)'!A2:A1000,"Everson")
A40: Nooksack businesses logged | B40: =COUNTIF(Prospects!A2:A1000,"Nooksack")+COUNTIF('Skipped (Reference)'!A2:A1000,"Nooksack")
A41: Deming businesses logged | B41: =COUNTIF(Prospects!A2:A1000,"Deming")+COUNTIF('Skipped (Reference)'!A2:A1000,"Deming")
A42: Concrete businesses logged | B42: =COUNTIF(Prospects!A2:A1000,"Concrete")+COUNTIF('Skipped (Reference)'!A2:A1000,"Concrete")
A43: Aberdeen businesses logged | B43: =COUNTIF(Prospects!A2:A1000,"Aberdeen")+COUNTIF('Skipped (Reference)'!A2:A1000,"Aberdeen")
A44: Hoquiam businesses logged | B44: =COUNTIF(Prospects!A2:A1000,"Hoquiam")+COUNTIF('Skipped (Reference)'!A2:A1000,"Hoquiam")
A45: Montesano businesses logged | B45: =COUNTIF(Prospects!A2:A1000,"Montesano")+COUNTIF('Skipped (Reference)'!A2:A1000,"Montesano")
A46: Chehalis businesses logged | B46: =COUNTIF(Prospects!A2:A1000,"Chehalis")+COUNTIF('Skipped (Reference)'!A2:A1000,"Chehalis")
A47: Centralia businesses logged | B47: =COUNTIF(Prospects!A2:A1000,"Centralia")+COUNTIF('Skipped (Reference)'!A2:A1000,"Centralia")
A48: Olympia businesses logged | B48: =COUNTIF(Prospects!A2:A1000,"Olympia")+COUNTIF('Skipped (Reference)'!A2:A1000,"Olympia")
A49: Lacey businesses logged | B49: =COUNTIF(Prospects!A2:A1000,"Lacey")+COUNTIF('Skipped (Reference)'!A2:A1000,"Lacey")
A50: Tumwater businesses logged | B50: =COUNTIF(Prospects!A2:A1000,"Tumwater")+COUNTIF('Skipped (Reference)'!A2:A1000,"Tumwater")
A51: Raymond businesses logged | B51: =COUNTIF(Prospects!A2:A1000,"Raymond")+COUNTIF('Skipped (Reference)'!A2:A1000,"Raymond")
A52: Long Beach businesses logged | B52: =COUNTIF(Prospects!A2:A1000,"Long Beach")+COUNTIF('Skipped (Reference)'!A2:A1000,"Long Beach")
A53: Enumclaw businesses logged | B53: =COUNTIF(Prospects!A2:A1000,"Enumclaw")+COUNTIF('Skipped (Reference)'!A2:A1000,"Enumclaw")
A54: Elma businesses logged | B54: =COUNTIF(Prospects!A2:A1000,"Elma")+COUNTIF('Skipped (Reference)'!A2:A1000,"Elma")
A55: McCleary businesses logged | B55: =COUNTIF(Prospects!A2:A1000,"McCleary")+COUNTIF('Skipped (Reference)'!A2:A1000,"McCleary")
A56: Westport businesses logged | B56: =COUNTIF(Prospects!A2:A1000,"Westport")+COUNTIF('Skipped (Reference)'!A2:A1000,"Westport")
A57: South Bend businesses logged | B57: =COUNTIF(Prospects!A2:A1000,"South Bend")+COUNTIF('Skipped (Reference)'!A2:A1000,"South Bend")
A58: Ellensburg businesses logged | B58: =COUNTIF(Prospects!A2:A1000,"Ellensburg")+COUNTIF('Skipped (Reference)'!A2:A1000,"Ellensburg")
A59: Cle Elum businesses logged | B59: =COUNTIF(Prospects!A2:A1000,"Cle Elum")+COUNTIF('Skipped (Reference)'!A2:A1000,"Cle Elum")
A60: Wenatchee businesses logged | B60: =COUNTIF(Prospects!A2:A1000,"Wenatchee")+COUNTIF('Skipped (Reference)'!A2:A1000,"Wenatchee")
A61: East Wenatchee businesses logged | B61: =COUNTIF(Prospects!A2:A1000,"East Wenatchee")+COUNTIF('Skipped (Reference)'!A2:A1000,"East Wenatchee")
A62: Sunnyside businesses logged | B62: =COUNTIF(Prospects!A2:A1000,"Sunnyside")+COUNTIF('Skipped (Reference)'!A2:A1000,"Sunnyside")
A63: Toppenish businesses logged | B63: =COUNTIF(Prospects!A2:A1000,"Toppenish")+COUNTIF('Skipped (Reference)'!A2:A1000,"Toppenish")
A64: Zillah businesses logged | B64: =COUNTIF(Prospects!A2:A1000,"Zillah")+COUNTIF('Skipped (Reference)'!A2:A1000,"Zillah")
A65: Yakima businesses logged | B65: =COUNTIF(Prospects!A2:A1000,"Yakima")+COUNTIF('Skipped (Reference)'!A2:A1000,"Yakima")
A67: How to use this tracker
A68: Prospects tab: every real outreach target (Hot/Warm/Watch), one row each.
A69: Skipped (Reference) tab: businesses already checked that don't need outreach right now.
A70: Flag column: Hot = no real working website + 4+ stars + 25+ reviews (best cold-call targets).
A71: Warm = bad/outdated/broken website + 4+ stars + 25+ reviews (good redesign pitch).
A72: Watch = meets quality bar but under 25 reviews - recheck as they grow.
A73: See research-playbook.md in this folder for the full methodology (domain verification steps,
A74: red-flag checklist, hub-town vs satellite-town logic).
A75: Confirmed satellite clusters (no independent market, served by nearby hub - don't search directly):
A76: Burlington/Granite Falls/Darrington/Gold Bar/Camano Island, and South Whidbey (Freeland/Langley/
A77: Coupeville, served by Oak Harbor's Island Heating & A&R HVAC), and Whatcom/Skagit Mt Baker Hwy
A78: corridor towns (Concrete, Everson, Nooksack, Deming - served by Ferndale/Lynden/Bellingham/Sedro-Woolley).
... A83: still yielded 3 Hot finds - see Round 7 learnings in research-playbook.md).

Sheet Skipped (Reference)
A1: City | B1: Business Name | C1: Phone | D1: Has Website | E1: Website URL | F1: Website Quality | G1: Google Rating | H1: Review Count | I1: Flag | J1: Owner Name | K1: Notes | L1: Source | M1: Date Found
A2: Arlington | B2: Ronk Brothers Heating, Cooling, and Electrical | C2: (360) 325-4416 | D2: Yes | E2: ronkheating.com | F2: Professional | G2: 4.9 | H2: 948 | I2: Skip | K2: Large 50+ yr regional multi-location company (Skagit/Snohomish/Whatcom); modern branded site, runs paid Google ads | L2: Google Maps; WebSearch | M2: 2026-07-02
A3: Arlington | B3: Cozy Heating Inc. | C3: (360) 803-8914 | D3: Yes | E3: cozyheatinginc.com | F3: Professional | G3: 4.9 | H3: 405 | I3: Skip | J3: Vincent Lee Sr Willett (L&I principal) | K3: Family-owned since 1979; clean modern site, clear CTAs, financing page | L3: Google Maps; WebSearch | M3: 2026-07-02
A4: Arlington | B4: Northern Comfort Heating & Cooling | C4: (425) 588-4139 | D4: Yes | E4: northerncomfortpros.com | F4: Professional | G4: 4.9 | H4: 280 | I4: Skip | K4: Modern branded site, 24/7 messaging, clean navigation | L4: Google Maps; WebSearch | M4: 2026-07-02
A5: Arlington | B5: Barron Heating AC Electrical & Plumbing | C5: (360) 386-7990 | D5: Yes | E5: barronheating.com | F5: Professional | G5: 4.9 | H5: 195 | I5: Skip | K5: Large 50-yr regional multi-service company HQ'd in Bellingham; polished corporate site | L5: Google Maps; WebSearch | M5: 2026-07-02
A6: Arlington | B6: Custom Floor Heating LLC | C6: (206) 624-0889 | D6: Yes | E6: customfloorheating.com | F6: Not assessed | G6: 4.1 | H6: 14 | I6: Skip | K6: Below both rating and review thresholds | L6: Google Maps | M6: 2026-07-02
A7: Arlington | B7: Cascade Climate | C7: (425) 923-9089 | D7: Yes | F7: Not assessed | G7: 5 | H7: 1 | I7: Skip | K7: Only 1 review - insufficient data to qualify | L7: Google Maps | M7: 2026-07-02
A8: Arlington (Mount Vernon HQ) | B8: Janes Radiant Heating | C8: (800) 974-5884 | D8: Yes | E8: janescompany.com | F8: Professional | G8: 4.7 | H8: 394 | I8: Skip | K8: Large radiant-heat specialist covering Western WA; well outside core small-shop target profile | L8: Google Maps | M8: 2026-07-02
A9: Marysville | B9: Product Air Heating, Cooling, and Electric | C9: (425) 340-3591 | D9: Yes | E9: productairheating.com | F9: Professional | G9: 5 | H9: 802 | I9: Skip | K9: Large, fast-growing, women-owned; just opened a Seattle office. Strong reviews and marketing presence | L9: Google Maps | M9: 2026-07-02
A10: Marysville | B10: Dapper Plumbing, Heating, and Electrical | C10: (360) 358-5754 | D10: Yes | E10: dapperplumbing.com | F10: Professional | G10: 4.8 | H10: 626 | I10: Skip | K10: Large multi-service plumbing/HVAC/electrical company, polished branded site | L10: Google Maps; direct site visit | M10: 2026-07-02
A11: Marysville | B11: South West Plumbing, Heating, Air & Electric | C11: (360) 939-8504 | D11: Yes | F11: Professional (large chain) | G11: 5 | H11: 2007 | I11: Skip | K11: Large regional multi-service chain | L11: Google Maps | M11: 2026-07-02
A12: Marysville | B12: Paragon Heating and Home Comfort Solutions | C12: (360) 658-9500 | D12: Yes | E12: paragonheating.com | F12: Professional | G12: 4.8 | H12: 131 | I12: Skip | K12: Custom branded logo, real photography, polished design | L12: Google Maps; WebSearch; direct site visit | M12: 2026-07-02
A13: Marysville (Renton HQ) | B13: Energy Saver Solutions LLC | C13: (206) 558-8070 | D13: Yes | E13: energysaversolutionswa.com | F13: Not assessed | G13: 5 | H13: 167 | I13: Skip | K13: HQ'd in Renton/Seattle area, not a genuinely local Marysville shop | L13: Google Maps | M13: 2026-07-02
A14: Marysville | B14: Topline Marysville HVAC Repair | C14: (360) 654-7362 | D14: Yes | F14: Not assessed | G14: 5 | H14: 4 | I14: Skip | K14: Only 4 reviews - insufficient data to qualify | L14: Google Maps | M14: 2026-07-02
A15: Marysville | B15: Parker Bros Heating and Cooling | C15: (360) 572-0108 | D15: Yes | F15: Not assessed | G15: 4.7 | H15: 18 | I15: Skip | K15: Below 30-review threshold | L15: Google Maps | M15: 2026-07-02
A16: Marysville | B16: Nordstrom Heating & Air, Inc | C16: (360) 386-8770 | D16: Yes | F16: Not assessed | G16: 5 | H16: 5 | I16: Skip | K16: Below 30-review threshold | L16: Google Maps | M16: 2026-07-02
A17: Marysville | B17: Polk Mechanical, LLC | C17: (425) 268-1471 | D17: Yes | F17: Not assessed | G17: 5 | H17: 15 | I17: Skip | K17: Below 30-review threshold | L17: Google Maps | M17: 2026-07-02
A18: Marysville | B18: Elevated HVAC Technologies L.L.C. | C18: (425) 892-3623 | D18: Yes | F18: Not assessed | G18: 5 | H18: 12 | I18: Skip | K18: Below 30-review threshold | L18: Google Maps | M18: 2026-07-02
A19: Stanwood | B19: Stilly River Mechanical, Inc. | C19: (360) 387-3788 | D19: Yes | E19: stillyrivermechanical.com | F19: Professional | G19: 4.9 | H19: 574 | I19: Skip | K19: Modern branded site, clean lead form, 18+ year family-owned company | L19: Google Maps; WebSearch; direct site visit | M19: 2026-07-02
A20: Stanwood | B20: Lobach HeatCoolX Systems | C20: (425) 345-3095 | D20: Yes | F20: Not assessed | G20: 5 | H20: 13 | I20: Skip | K20: Below 30-review threshold | L20: Google Maps | M20: 2026-07-02
A21: Stanwood | B21: All-Ways Air Control | C21: (360) 939-2637 | D21: No | F21: N/A | G21: 3.2 | H21: 9 | I21: Skip | K21: Below both rating and review thresholds | L21: Google Maps | M21: 2026-07-02
A22: Stanwood | B22: Ronk Brothers Heating (Stanwood location) | C22: (360) 855-1025 | D22: Yes | E22: ronkheating.com | F22: Professional | G22: 0 | H22: 0 | I22: Skip | K22: No reviews yet at this location; part of the large Ronk Brothers group already flagged Skip in Arlington | L22: Google Maps | M22: 2026-07-02
A23: Stanwood (Whidbey/Fidalgo focus) | B23: Island Ductless Heat Pumps | C23: (360) 321-4252 | D23: Yes | E23: islandheatpumps.com | F23: Not assessed | G23: 4.9 | H23: 171 | I23: Skip | K23: Primarily serves Whidbey/Fidalgo Island communities, not a core Stanwood-area shop | L23: Google Maps; WebSearch | M23: 2026-07-02
A24: Stanwood | B24: Prince Mechanical | C24: (360) 965-9157 | D24: Yes | F24: Not assessed | G24: 5 | H24: 2 | I24: Skip | K24: Only 2 reviews - insufficient data | L24: Google Maps | M24: 2026-07-02
A25: Mount Vernon | B25: Foss Heating & Cooling | C25: (360) 336-1517 | D25: Yes | E25: fossheating.com | F25: Not deeply assessed (large, established) | G25: 4.9 | H25: 956 | I25: Skip | K25: Large, long-established Skagit County company with strong review volume; presumed professional web presence | L25: Google Maps | M25: 2026-07-02
A26: Mount Vernon | B26: CPI Plumbing & Heating | C26: (360) 447-6675 | D26: Yes | F26: Not deeply assessed (large) | G26: 4.8 | H26: 3080 | I26: Skip | K26: Very large multi-service plumbing/HVAC company | L26: Google Maps | M26: 2026-07-02
A27: Mount Vernon | B27: CM Heating | C27: (360) 535-7277 | D27: Yes | E27: cmheating.com | F27: Professional (large chain) | G27: 5 | H27: 1205 | I27: Skip | K27: Large Snohomish/Skagit multi-service HVAC/plumbing/electrical chain | L27: Google Maps | M27: 2026-07-02
A28: Mount Vernon | B28: Mount Vernon HVAC Pros | C28: (360) 382-4170 | D28: No | F28: N/A | G28: 5 | H28: 1 | I28: Skip | K28: Only 1 review - insufficient data to qualify | L28: Google Maps | M28: 2026-07-02
A29: Mount Vernon | B29: R & H Mechanical Inc | C29: (360) 757-6909 | D29: Yes | E29: rhmech.com | F29: Professional | G29: 4.4 | H29: 51 | I29: Skip | K29: Clean modern site, real photography, since 1976 | L29: Google Maps; WebSearch; direct site visit | M29: 2026-07-02
A30: Mount Vernon | B30: SUNDANCE Energy | C30: (360) 295-9300 | D30: Yes | F30: Not assessed | G30: 4.2 | H30: 17 | I30: Skip | K30: Below 30-review threshold | L30: Google Maps | M30: 2026-07-02
A31: Mount Vernon | B31: All Phase Heating and Air Conditioning Inc. | C31: (360) 707-8521 | D31: Yes | F31: Not assessed | G31: 4.5 | H31: 16 | I31: Skip | K31: Below 30-review threshold | L31: Google Maps | M31: 2026-07-02
A32: Everett | B32: Home Comfort Alliance - Everett | C32: (425) 250-8005 | D32: Yes | E32: homecomfortalliance.com | F32: Professional (large chain) | G32: 4.8 | H32: 1776 | I32: Skip | K32: Large multi-city company running paid Google Ads | L32: Google Maps | M32: 2026-07-02
A33: Everett | B33: Greenwood Heating and Home Services | C33: (206) 207-4734 | D33: Yes | E33: greenwoodheating.com | F33: Not deeply assessed (large, established) | G33: 4.7 | H33: 210 | I33: Skip | K33: Full-service HVAC/electrical/plumbing company serving Everett since 1921 | L33: Google Maps; WebSearch | M33: 2026-07-02
A34: Everett | B34: North Heat & Air | C34: (425) 550-2203 | D34: Yes | E34: northheatair.com | F34: Professional | G34: 4.9 | H34: 39 | I34: Skip | K34: Modern branded site with real truck/team photography | L34: Google Maps; WebSearch; direct site visit | M34: 2026-07-02
A35: Everett | B35: Holy Moly Electric Plumbing Heating Air | C35: (425) 908-0030 | D35: Yes | F35: Not deeply assessed (large multi-service) | G35: 4.7 | H35: 328 | I35: Skip | K35: Large multi-service electric/plumbing/HVAC operator | L35: Google Maps | M35: 2026-07-02
A36: Everett | B36: Sound Comfort Heating and Air Conditioning | C36: (425) 225-4756 | D36: Yes | E36: soundcomfortheating.com | F36: Professional | G36: 5 | H36: 171 | I36: Skip | K36: Clean modern site with lead form and financing messaging | L36: Google Maps; WebSearch; direct site visit | M36: 2026-07-02
A37: Everett | B37: Eco Electric, Plumbing, Heating and Air | C37: (206) 800-6975 | D37: Yes | F37: Not deeply assessed (large multi-service) | G37: 4.9 | H37: 309 | I37: Skip | K37: Large multi-service electric/plumbing/HVAC operator | L37: Google Maps | M37: 2026-07-02
A38: Everett | B38: Northwest Thermal Solutions | C38: (425) 530-9488 | D38: Yes | F38: Not assessed | G38: 5 | H38: 4 | I38: Skip | K38: Only 4 reviews - insufficient data | L38: Google Maps | M38: 2026-07-02
A39: Everett | B39: Better Air NW Heating & Cooling | C39: (206) 898-5743 | D39: Yes | E39: betterairnw.com | F39: Not deeply assessed (large, established) | G39: 4.9 | H39: 412 | I39: Skip | K39: Woman-run company since 2009, strong review volume and marketing presence | L39: Google Maps; WebSearch | M39: 2026-07-02
A40: Everett | B40: Washington Energy Services | C40: (800) 398-4663 | D40: Yes | E40: washingtonenergy.com | F40: Not deeply assessed (very large) | G40: 4.7 | H40: 911 | I40: Skip | K40: Very large regional home-services company running paid Google Ads | L40: Google Maps | M40: 2026-07-02
A41: Everett | B41: ExactAir Home Comfort | C41: (425) 232-9878 | D41: Yes | F41: Not assessed | G41: 5 | H41: 11 | I41: Skip | K41: Below 30-review threshold | L41: Google Maps | M41: 2026-07-02
A43: These already have a solid site, are too large/established, or fall outside the core target profile. Moved here to keep the main Prospects tab focused on real outreach targets.
A44: Lake Stevens | B44: 1st Response HVAC & Electric Solutions | C44: (206) 643-1525 | D44: Yes | E44: 1stresponsehvac.com | F44: Professional | G44: 4.6 | H44: 177 | I44: Skip | K44: Real team branding and photography, decent modern design | L44: Google Maps; WebSearch; direct site visit | M44: 2026-07-02
A45: Lake Stevens | B45: Altitude Heating and Cooling | C45: (425) 201-1998 | D45: Yes | E45: altitudeheating.com | F45: Professional | G45: 5 | H45: 56 | I45: Skip | K45: Modern branded logo, real Google reviews embedded on homepage, clean layout | L45: Google Maps; WebSearch; direct site visit | M45: 2026-07-02
A46: Lake Stevens | B46: Beck's Furnace Inc. | C46: (425) 353-2789 | D46: Yes | E46: becksfurnace.com | F46: Professional | G46: 4.9 | H46: 69 | I46: Skip | K46: Clean design, real branded truck photography, family owned since 1973 | L46: Google Maps; WebSearch; direct site visit | M46: 2026-07-02
A47: Lake Stevens | B47: Beaver Heating & Air, LLC | C47: (360) 502-5203 | D47: Yes | E47: beaverheatingwa.com | F47: Professional | G47: 4.9 | H47: 113 | I47: Skip | K47: Real team photo, modern branded layout serving Snohomish/Skagit/Whatcom | L47: Google Maps; WebSearch; direct site visit | M47: 2026-07-02
A48: Lake Stevens | B48: Good Guys Heating, Air and Electrical | C48: (425) 496-7300 | D48: Yes | E48: goodguysheatingairandelectrical.com | F48: Professional | G48: 4.9 | H48: 147 | I48: Skip | J48: Seth T. Swetman | K48: Active site is modern and clean. Note: an old/expired domain (goodguysheating.com) is now parked for sale on GoDaddy - not their real site, but could confuse people searching by name | L48: Google Maps; WebSearch; direct site visit | M48: 2026-07-02
A49: Lake Stevens | B49: Right On Heating & Sheet Metal Inc. | C49: (425) 335-4207 | D49: Yes | F49: Not assessed | G49: 4.6 | H49: 21 | I49: Skip | K49: Below 30-review threshold | L49: Google Maps | M49: 2026-07-02
A50: Lake Stevens | B50: Cascade Comfort Systems LLC | C50: (425) 583-3168 | D50: No | F50: N/A | G50: 5 | H50: 1 | I50: Skip | K50: Only 1 review - insufficient data | L50: Google Maps | M50: 2026-07-02
A51: Lake Stevens | B51: PNW Fresh Air | C51: (425) 765-5513 | D51: Yes | F51: Not assessed | G51: 4.9 | H51: 227 | I51: Skip | K51: Air duct cleaning service, not a core HVAC install/repair contractor | L51: Google Maps | M51: 2026-07-02
A52: Lake Stevens | B52: Alaka'i Air LLC | C52: (425) 565-0388 | D52: Yes | F52: Not assessed | G52: 5 | H52: 21 | I52: Skip | K52: Below 30-review threshold | L52: Google Maps | M52: 2026-07-02
A53: Lake Stevens | B53: Ridgeline Heating and Cooling | C53: (844) 200-7045 | D53: Yes | F53: Not assessed | G53: 5 | H53: 20 | I53: Skip | K53: Below 30-review threshold | L53: Google Maps | M53: 2026-07-02
A54: Snohomish | B54: Lifetime Heating, Cooling, Plumbing and Electric | C54: (425) 270-8830 | D54: Yes | F54: Not deeply assessed (very large) | G54: 4.9 | H54: 1714 | I54: Skip | K54: Very large regional multi-service company | L54: Google Maps | M54: 2026-07-02
A55: Snohomish | B55: All Heating | C55: (425) 743-5000 | D55: Yes | F55: Not deeply assessed (large) | G55: 4.9 | H55: 706 | I55: Skip | K55: Large established Snohomish County company | L55: Google Maps | M55: 2026-07-02
A56: Snohomish | B56: Snohomish Valley Electric, Heat & AC | C56: (360) 294-8276 | D56: Yes | F56: Not assessed | G56: 4.5 | H56: 24 | I56: Skip | K56: Below 30-review threshold | L56: Google Maps | M56: 2026-07-02
A57: Lynnwood | B57: CM Heating (Lynnwood) | C57: (425) 600-7767 | D57: Yes | E57: cmheating.com | F57: Professional (large chain) | G57: 4.9 | H57: 569 | I57: Skip | K57: Large Snohomish/King multi-service HVAC/plumbing/electrical chain | L57: Google Maps | M57: 2026-07-02
A58: Lynnwood | B58: Kings Heating, Air & Electric | C58: (425) 224-7623 | D58: Yes | F58: Not deeply assessed (large) | G58: 4.9 | H58: 730 | I58: Skip | K58: Large established company | L58: Google Maps | M58: 2026-07-02
A59: Lynnwood | B59: Washington Energy Services (Lynnwood) | C59: (800) 398-4663 | D59: Yes | E59: washingtonenergy.com | F59: Not deeply assessed (very large) | G59: 4.7 | H59: 914 | I59: Skip | K59: Very large regional home-services company running paid ads | L59: Google Maps | M59: 2026-07-02
A60: Lynnwood | B60: Brennan Heating, Air Conditioning, & Electric | C60: (425) 553-2612 | D60: Yes | F60: Not deeply assessed (large) | G60: 4.8 | H60: 378 | I60: Skip | K60: Large multi-service company | L60: Google Maps | M60: 2026-07-02
A61: Lynnwood | B61: Blue Flame Heating & Air Conditioning | C61: (425) 264-8896 | D61: Yes | F61: Not deeply assessed (very large) | G61: 4.4 | H61: 2258 | I61: Skip | K61: Very large regional company | L61: Google Maps | M61: 2026-07-02
A62: Lynnwood | B62: Day & Nite Plumbing & Heating, Inc. | C62: (425) 678-6026 | D62: Yes | F62: Not deeply assessed (very large) | G62: 4.8 | H62: 1772 | I62: Skip | K62: Very large regional plumbing/HVAC company | L62: Google Maps | M62: 2026-07-02
A63: Edmonds | B63: Randall Air Conditioning & Heating | C63: (425) 725-3073 | D63: Yes | E63: randallacnottingham.com | F63: Professional | G63: 5 | H63: 31 | I63: Skip | K63: Clean minimal modern design despite an unusual domain name | L63: Google Maps; WebSearch; direct site visit | M63: 2026-07-02
A64: Edmonds | B64: AirGanic | C64: (206) 747-4769 | D64: Yes | E64: airganic.com | F64: Professional | G64: 4.8 | H64: 315 | I64: Skip | K64: Polished modern site with real photography | L64: Google Maps; WebSearch; direct site visit | M64: 2026-07-02
A65: Edmonds | B65: Adam&Sam brothers repair - Appliance & Refrigeration | C65: (425) 570-9520 | D65: No | F65: N/A | G65: 4.8 | H65: 28 | I65: Skip | K65: Below 30-review threshold | L65: Google Maps | M65: 2026-07-02
A66: Edmonds | B66: Olympic | C66: (425) 670-3900 | D66: No | F66: N/A | G66: 5 | H66: 13 | I66: Skip | K66: Below 30-review threshold - insufficient data | L66: Google Maps | M66: 2026-07-02
A67: Monroe | B67: Heating & Air Conditioning Monroe | C67: (206) 339-5860 | D67: No | F67: N/A | G67: 5 | H67: 8 | I67: Skip | K67: Below 30-review threshold | L67: Google Maps | M67: 2026-07-02
A68: Monroe | B68: Johansen Mechanical Inc | C68: (425) 481-2266 | D68: Yes | F68: Not assessed | G68: 4 | H68: 19 | I68: Skip | K68: Below both rating and review thresholds | L68: Google Maps | M68: 2026-07-02
A69: Monroe | B69: Z-Man Services | D69: No | F69: N/A | G69: 4 | H69: 2 | I69: Skip | K69: Below both rating and review thresholds | L69: Google Maps | M69: 2026-07-02
A70: Monroe | B70: ACM Cooling and Heating | C70: (425) 518-3225 | D70: Yes | F70: Not assessed | G70: 5 | H70: 6 | I70: Skip | K70: Below 30-review threshold | L70: Google Maps | M70: 2026-07-02
A71: Oak Harbor | B71: Island Heating & A/C Inc. | C71: (360) 230-1352 | D71: Yes | E71: islandheatingac.com | F71: Professional | G71: 4.6 | H71: 312 | I71: Skip | J71: Patrick J Dipzinski (L&I principal) | K71: Real branded logo, clean lead form, 40+ years in business | L71: Google Maps; WebSearch; direct site visit | M71: 2026-07-02
A72: Oak Harbor | B72: Trico Heating Inc | C72: (360) 675-2700 | D72: No | F72: N/A | G72: 4.7 | H72: 13 | I72: Skip | K72: Below 30-review threshold | L72: Google Maps | M72: 2026-07-02
A73: Sedro-Woolley | B73: Rick's Refrigeration | C73: (360) 856-1798 | D73: No | F73: N/A | G73: 3.7 | H73: 3 | I73: Skip | K73: Below both rating and review thresholds | L73: Google Maps | M73: 2026-07-02
A74: Sedro-Woolley | B74: Pacific Northwest Refrigeration & Heating | C74: (360) 630-6571 | D74: Yes | F74: Not assessed | G74: 5 | H74: 1 | I74: Skip | K74: Only 1 review - insufficient data | L74: Google Maps | M74: 2026-07-02
A75: Sultan | B75: Q & Q Climate Systems | C75: (425) 595-0488 | D75: Yes | E75: qqclimatesystemswa.com | F75: Professional | G75: 5 | H75: 44 | I75: Skip | K75: Modern clean design, real CTA buttons, minor icon-font glitch but overall polished | L75: Google Maps; WebSearch; direct site visit | M75: 2026-07-02
A76: Camano Island | B76: Thomas Mechanical LLC | C76: (425) 905-9882 | D76: Yes | F76: Not assessed | G76: 4.4 | H76: 7 | I76: Skip | K76: Below 30-review threshold | L76: Google Maps | M76: 2026-07-02
A77: Camano Island | B77: Marshall's Heating & AC | C77: (360) 331-1859 | D77: Yes | F77: Not assessed | G77: 4.4 | H77: 12 | I77: Skip | K77: Below 30-review threshold | L77: Google Maps | M77: 2026-07-02
A78: Anacortes | B78: LaVergne's Plumbing & Heating | C78: (360) 226-2445 | D78: Yes | E78: lavergneplumbing.com | F78: Professional | G78: 4.6 | H78: 303 | I78: Skip | K78: Clean modern site, branded logo, family-owned since 1951 | L78: Google Maps; WebSearch; direct site visit | M78: 2026-07-02
A79: Anacortes | B79: Washington Air Conditioning Systems | C79: (360) 298-7942 | D79: No | F79: N/A | G79: 5 | H79: 2 | I79: Skip | K79: Only 2 reviews - insufficient data | L79: Google Maps | M79: 2026-07-02
A80: Anacortes | B80: Jacobson Heating & Air Conditioning LLC | C80: (360) 855-1025 | D80: No | F80: N/A | G80: 3.5 | H80: 8 | I80: Skip | K80: Below both rating and review thresholds | L80: Google Maps | M80: 2026-07-02
A81: Mukilteo | B81: Legacy One Heating | C81: (425) 906-3447 | D81: Yes | E81: legacyoneheating.net | F81: Professional | G81: 4.7 | H81: 69 | I81: Skip | K81: Branded logo, decent modern design (two-tier nav is a minor knock but not enough alone) | L81: Google Maps; WebSearch; direct site visit | M81: 2026-07-02
A82: Mukilteo | B82: Chill Mechanical | C82: (253) 424-4218 | D82: Yes | F82: Not assessed | G82: 5 | H82: 6 | I82: Skip | K82: Below 30-review threshold | L82: Google Maps | M82: 2026-07-02
A83: South Whidbey (Freeland) | B83: Energywise Ductless Heat Pumps LLC | C83: (360) 661-7191 | D83: Yes | E83: energywisedhp.com | F83: Professional | G83: 5 | H83: 50 | I83: Skip | K83: Clean modern design, real CTAs, based in Clinton WA | L83: Google Maps; WebSearch; direct site visit | M83: 2026-07-02
A84: South Whidbey (Freeland) | B84: South Whidbey Services LLC | C84: (360) 499-6543 | D84: Yes | F84: Not assessed | G84: 5 | H84: 2 | I84: Skip | K84: Only 2 reviews - insufficient data | L84: Google Maps | M84: 2026-07-02
A85: South Whidbey (Langley) | B85: AP Mechanical | C85: (360) 321-6914 | D85: Yes | F85: Not assessed | G85: 5 | H85: 5 | I85: Skip | K85: Below 30-review threshold | L85: Google Maps | M85: 2026-07-02
A86: Bellingham | B86: Marr's Heating, AC, Plumbing & Electrical | C86: (855) 202-7062 | D86: Yes | F86: Not deeply assessed (very large) | G86: 4.9 | H86: 1952 | I86: Skip | K86: Very large regional multi-service company | L86: Google Maps | M86: 2026-07-02
A87: Bellingham | B87: West Mechanical Heating Cooling Electrical, Plumbing | C87: (360) 734-7599 | D87: Yes | F87: Not deeply assessed (very large) | G87: 4.9 | H87: 1329 | I87: Skip | K87: Very large regional multi-service company | L87: Google Maps | M87: 2026-07-02
A88: Bellingham | B88: Feller Heating & Air Conditioning | C88: (360) 733-4827 | D88: Yes | E88: fellerheating.com | F88: Professional | G88: 4.8 | H88: 274 | I88: Skip | J88: Steve M Felbinger (L&I principal) | K88: Modern redesigned site (was flagged dated in an earlier internal review, appears since updated) - clean layout, real domain email, clear CTAs | L88: Google Maps; WebSearch; direct site visit | M88: 2026-07-02
A89: Bellingham | B89: Clean Air Heating & Cooling | C89: (360) 398-9400 | D89: Yes | F89: Not deeply assessed (very large) | G89: 4.9 | H89: 857 | I89: Skip | K89: Very large regional company | L89: Google Maps | M89: 2026-07-02
A90: Snohomish | B90: Glacier Heating & Cooling | C90: (425) 422-8861 | D90: Yes | E90: glacierheating.com | F90: Professional - modern design, real branded logo (mountain/bear mascot), real photo of their own branded box truck, clean layout, embedded Google rating badge | G90: 5 | H90: 29 | I90: Skip | K90: 29 reviews clears the new 25+ bar, but site is professional and modern - not a realistic client | L90: Google Maps | M90: 2026-07-02
A91: Bellingham | B91: LSM Heating, Plumbing, Electric, Inc. | C91: (360) 354-3991 | D91: Yes | E91: lyndensheetmetal.com | F91: Professional - modern, well-established multi-service site (86 years in business, 60+ service vehicles, 60+ technicians, financing options, warranties, testimonials, brand partnerships). Large regional company, not a realistic small-business client. | G91: 5 | H91: 27 | I91: Skip | K91: 27 reviews clears the new 25+ bar, but this is a large, established multi-county operation (since 1940) with a professional, modern site - too large/corporate to be a realistic ProBook client | L91: Google Maps | M91: 2026-07-02
A92: Bremerton | B92: Advanced Heating & Cooling, Inc. | C92: (833) 241-5723 | D92: Yes | F92: Professional (large chain, 24hr, book online) | G92: 4.8 | H92: 483 | I92: Skip | K92: Large established operation, 483 reviews - not a realistic small-business client | L92: Google Maps | M92: 2026-07-02
A93: Bremerton | B93: Home Comfort Alliance - Bremerton | C93: (360) 209-1919 | D93: Yes | F93: Professional (large chain) | G93: 4.8 | H93: 420 | I93: Skip | K93: Large established regional franchise-style operation | L93: Google Maps | M93: 2026-07-02
A94: Bremerton | B94: Peninsula Heating And Cooling | C94: (360) 613-5866 | D94: Yes | F94: Professional (large established) | G94: 4.8 | H94: 436 | I94: Skip | K94: Large review count, established | L94: Google Maps | M94: 2026-07-02
A95: Bremerton | B95: Dana's Heating & Cooling, Inc. | C95: (360) 226-7369 | D95: Yes | F95: Professional (huge chain) | G95: 4.9 | H95: 3320 | I95: Skip | K95: 3,320 reviews - major established operation | L95: Google Maps | M95: 2026-07-02
A96: Bremerton | B96: Economy Hearth & Home Inc. | C96: (360) 692-8709 | D96: Yes | F96: Professional (large established) | G96: 4.8 | H96: 356 | I96: Skip | K96: Large review count, established; also serves Silverdale | L96: Google Maps | M96: 2026-07-02
A97: Bremerton | B97: Randy's Heating | C97: (360) 621-6915 | D97: Yes | E97: randysheating.repair | F97: Professional - modern financing CTA, clean branded design | G97: 4.9 | H97: 180 | I97: Skip | K97: Professional modern site | L97: Google Maps; WebSearch | M97: 2026-07-02
A98: Bremerton | B98: JET Heating and Cooling | C98: (360) 813-1288 | D98: Yes | E98: jetheatingandcooling.com | F98: Professional - modern site, financing CTA; only 1 red flag (gmail contact) - not enough to flag Warm | G98: 4.7 | H98: 127 | I98: Skip | K98: Professional site, single red flag not enough for Warm | L98: Google Maps; WebSearch | M98: 2026-07-02
A99: Port Orchard | B99: Air Masters Heating & Cooling | C99: (360) 895-2527 | D99: Yes | E99: airmastersheating.com | F99: Professional - brand-partner logos (Lennox/Mitsubishi/Diamond Contractor), real team/van photo | G99: 4.8 | H99: 161 | I99: Skip | J99: Mark A Timmerman (L&I principal) | K99: Professional site, 11-50 employees per LinkedIn | L99: Google Maps; WebSearch | M99: 2026-07-02
A100: Port Orchard | B100: Gold Mountain Air | C100: (360) 228-8545 | D100: Yes | E100: goldmountainair.com | F100: Professional - modern branded site, real work photo, clean nav | G100: 4.9 | H100: 133 | I100: Skip | K100: Professional site | L100: Google Maps; WebSearch | M100: 2026-07-02
A101: Port Orchard | B101: Smart Climate HVAC | C101: (360) 622-0103 | D101: Yes | F101: Too new to assess | G101: 5 | H101: 2 | I101: Skip | K101: Too few reviews/too new | L101: Google Maps | M101: 2026-07-02
...

Sheet L&I Goldmine
A1: Business Name | B1: City | C1: Phone | D1: License Since | E1: Years Licensed | F1: Already in Sheet? | G1: Triage Result | H1: Notes | I1: Geo Tier
A2: L & K Heating | B2: Nine Mile Falls | C2: 5097685601 | D2: 1981-03-19 | E2: 45.3 | G2: Hot - logged | I2: 1
A3: Todd Sheet Metal | B3: Suquamish | C3: 3605984517 | D3: 1981-07-01 | E3: 45 | G3: Hot - logged | I3: 1
A4: Action Heating/Air Condtng | B4: Carnation | C4: 4254511464 | D4: 1983-07-15 | E4: 43 | G4: Watch - logged | I4: 1
A5: Comfort Mechanical Contrs Inc | B5: Greenacres | C5: 5099280207 | D5: 1997-05-07 | E5: 29.2 | G5: Watch - logged | I5: 1
A6: Naylors Appliance & Refrigertn | B6: Tonasket | C6: 5094862351 | D6: 1997-08-22 | E6: 28.9 | G6: Hot - logged | I6: 1
A7: Dr Cool Inc | B7: Sumner | C7: 2538635665 | D7: 1998-11-05 | E7: 27.7 | G7: Skip - logged | I7: 1
A8: Action Plumbing & Htg Inc | B8: Dryden | C8: 5095484458 | D8: 2000-02-28 | E8: 26.3 | G8: Watch - logged | I8: 1
A9: Carlson'S Heating & A/C Inc | B9: Kelso | C9: 3604254888 | D9: 2000-02-28 | E9: 26.3 | G9: Skip - logged | I9: 1
A10: Mantey Heating | B10: Moxee | C10: 5099665520 | D10: 2000-02-28 | E10: 26.3 | G10: Skip - logged (closed) | I10: 1
A11: Accent Heating & Cooling Llc | B11: Brush Prairie | C11: 3608851940 | D11: 2000-03-01 | E11: 26.3 | G11: Warm - logged | I11: 1
A12: Morris Plumbing & Heating | B12: Eastsound | C12: 3603176104 | D12: 2000-03-01 | E12: 26.3 | G12: Hot - logged | I12: 1
A13: Action Heating & Air Cond | B13: Carnation | C13: 4254511464 | D13: 2000-03-02 | E13: 26.3 | G13: Watch - logged | I13: 1
A14: Twin City Srvc Co Inc | B14: Kelso | C14: 3604253320 | D14: 2000-04-24 | E14: 26.2 | G14: Warm - logged | H14: PASF intel 2026-07-02: GMB "Twin City Service Co" 4.9/74 - meets bar, check website when triaged | I14: 1
A15: Sea Aire Inc | B15: Algona | C15: 2065758051 | D15: 2000-05-12 | E15: 26.1 | G15: Skip - logged | I15: 1
A16: Naylor'S Appliance/Refrig Inc | B16: Tonasket | C16: 5094862351 | D16: 2000-05-15 | E16: 26.1 | G16: Hot - logged | I16: 1
A17: Comfort Air Systems | B17: Orting | C17: 2532274670 | D17: 2000-06-28 | E17: 26 | G17: Skip - logged | I17: 1
A18: Orca Heating & A/C | B18: Quil Ceda Village | C18: 4253599208 | D18: 2001-03-08 | E18: 25.3 | G18: RE-CHECK - phone mismatch vs GMB | H18: L&I ph 4253599208 != Tulalip GMB 4255082484; skipped GMB may be different company. Call L&I number. | I18: 1
A19: Freels Refrigeration | B19: Omak | C19: 5098265492 | D19: 2001-03-21 | E19: 25.3 | G19: Hot - logged | I19: 1
A20: Terry'S Appliance Service | B20: Winthrop | C20: 5099963741 | D20: 2001-06-29 | E20: 25 | G20: Skip - logged | I20: 1
A21: Olympic Heating & Cooling Llc | B21: Shelton | C21: 3604269945 | D21: 2001-12-31 | E21: 24.5 | G21: Skip - logged | I21: 1
A22: D K Systems Inc | B22: Burlington | C22: 3607551555 | D22: 2002-07-26 | E22: 23.9 | G22: Watch - logged | I22: 1
A23: Compass Mechanical Llc | B23: Coulee City | C23: 5097592321 | D23: 2002-08-02 | E23: 23.9 | G23: Hot - logged | I23: 1
A24: T & M Heating & Refrig Inc | B24: Union Gap | C24: 5095751088 | D24: 2002-08-19 | E24: 23.9 | G24: Hot - logged | I24: 1
A25: Tradesman'S Mechanical Service | B25: Oakville | C25: 3602809270 | D25: 2002-12-19 | E25: 23.5 | G25: Hot - logged | I25: 1
A26: Thermal Air Llc | B26: Oroville | C26: 5094763145 | D26: 2003-04-02 | E26: 23.2 | G26: Hot - logged | I26: 1
A27: Allencraft Enterprise | B27: Morton | C27: 3604963244 | D27: 2003-05-06 | E27: 23.2 | G27: Skip - logged | I27: 1
A28: Central Energy Products Llc | B28: Ephrata | C28: 5097602882 | D28: 2003-08-19 | E28: 22.9 | G28: Hot - logged | I28: 1
A29: Refresh Llc | B29: North Bend | C29: 4254503222 | D29: 2003-12-18 | E29: 22.5 | G29: Hot - logged | I29: 1
A30: Lopez Heating Systems | B30: Lopez Island | C30: 3604682574 | D30: 2004-02-05 | E30: 22.4 | G30: Hot - logged | I30: 1
A31: Gfr Heating & Cooling Llc | B31: Milton | C31: 2062443996 | D31: 2005-02-14 | E31: 21.4 | G31: Watch - logged | I31: 1
A32: R & H Mechanical Inc | B32: Burlington | C32: 3607576909 | D32: 2005-06-03 | E32: 21.1 | F32: Yes | I32: 1
A33: All Weather Htg A/C & Rfrg Llc | B33: Snoqualmie | C33: 4254639814 | D33: 2006-01-04 | E33: 20.5 | G33: Skip - logged | I33: 1
A34: All Weather Htg A/C/Refrig Llc | B34: Snoqualmie | C34: 4254639814 | D34: 2006-01-04 | E34: 20.5 | G34: Skip - logged (dup row) | I34: 1
A35: Americool Heating And A/C Llc | B35: Rochester | C35: 3602733300 | D35: 2006-01-27 | E35: 20.4 | G35: Skip - logged | I35: 1
A36: Dunsmore Heating & Gas Piping | B36: Clinton | C36: 3602218567 | D36: 2006-02-28 | E36: 20.3 | G36: Hot - logged | I36: 1
A37: Heating Guy Inc | B37: Deming | C37: 3609274643 | D37: 2006-03-24 | E37: 20.3 | F37: Yes | I37: 1
A38: North Cascades Htg & A/C Inc | B38: Entiat | C38: 5097844822 | D38: 2006-04-11 | E38: 20.2 | G38: Skip - logged | I38: 1
A39: Freedom Heating And Ac Llc | B39: Mccleary | C39: 3604702888 | D39: 2006-06-15 | E39: 20 | G39: Hot - logged | I39: 1
A40: Kimball Mechanical | B40: Snoqualmie | C40: 4258644745 | D40: 2006-07-21 | E40: 19.9 | G40: Hot - logged | I40: 1
A41: Flameworks Inc | B41: Veradale | C41: 5097100674 | D41: 2007-02-13 | E41: 19.4 | G41: Hot - logged | I41: 1
A42: Shrode Heating & Cooling Inc | B42: Rosalia | C42: 5095234838 | D42: 2007-06-06 | E42: 19.1 | G42: Hot - logged | I42: 1
A43: Economy Air Systems Inc | B43: Tracyton | C43: 3606986626 | D43: 2007-06-25 | E43: 19 | G43: Watch - logged | I43: 1
A44: Whidbey Heating & Stoves Llc | B44: Greenbank | C44: 3606615376 | D44: 2007-06-26 | E44: 19 | G44: Skip - logged | I44: 1
A45: Airtight Htg & A/C Llc | B45: East Olympia | C45: 3604550455 | D45: 2007-10-02 | E45: 18.7 | G45: Hot - logged | I45: 1
A46: Custom Heating & Cooling Llc | B46: Kelso | C46: 3606361850 | D46: 2007-10-17 | E46: 18.7 | G46: Skip - logged (PASF 2.1/7) | I46: 1
A47: Hydrosci Llc | B47: Mead | C47: 5094640531 | D47: 2008-03-20 | E47: 18.3 | G47: Hot - logged | I47: 1
A48: Anderson Nesler Company Inc | B48: Milton | C48: 2533818456 | D48: 2008-04-17 | E48: 18.2 | G48: Hot - logged | I48: 1
A49: Norstar Heating & Cooling Inc | B49: Colville | C49: 5096844291 | D49: 2008-06-17 | E49: 18 | F49: Yes | I49: 1
A50: Reliatemp Llc | B50: Belfair | C50: 3602754793 | D50: 2008-07-25 | E50: 17.9 | G50: Hot - logged | I50: 1
A51: Denali Heating & A/C Llc | B51: Castle Rock | C51: 3602748049 | D51: 2009-03-31 | E51: 17.3 | G51: Skip - logged | I51: 1
A52: San Juan Heating Llc | B52: Friday Harbor | C52: 3603784328 | D52: 2009-10-22 | E52: 16.7 | G52: Watch - logged | I52: 1
A53: Systech Mechanical Llc | B53: Chewelah | C53: 5099354328 | D53: 2010-04-23 | E53: 16.2 | G53: Skip - logged | I53: 1
A54: House Doctors | B54: Blaine | C54: 3603199625 | D54: 2010-07-15 | E54: 16 | G54: Hot - logged | I54: 1
A55: Rawhide Electric Services Llc | B55: Woodland | C55: 3605773860 | D55: 2010-12-03 | E55: 15.6 | G55: Skip - logged | I55: 1
A56: Testing & Comm. Services Llc | B56: Bow | C56: 3602248555 | D56: 2011-03-30 | E56: 15.3 | G56: Skip - logged (name pre-filter) | I56: 1
A57: Air Flo Heating Company Inc | B57: Sequim | C57: 3606833901 | D57: 1980-03-07 | E57: 46.3 | F57: Yes | I57: 2
A58: Norco Heating & Air Cond Inc | B58: Spokane | C58: 5095344975 | D58: 1983-12-09 | E58: 42.6 | G58: Skip - logged | I58: 2
A59: Advanced Mechanical Sys Inc | B59: Spokane Valley | C59: 5095340547 | D59: 1984-11-13 | E59: 41.6 | G59: Skip - logged | I59: 2
A60: Monroe Heating & Refrigeration | B60: Snohomish | C60: 3607947914 | D60: 1985-05-07 | E60: 41.2 | G60: Hot - logged | I60: 2
A61: Lloyd'S Heating & Sheetmetal | B61: Enumclaw | C61: 3608252241 | D61: 1990-07-30 | E61: 35.9 | F61: Yes | I61: 2
A62: Tim'S Comfort Plus | B62: Spokane | C62: 5095346558 | D62: 1991-05-17 | E62: 35.1 | G62: Hot - logged | I62: 2
A63: Salazar Specialized Services | B63: Yakima | C63: 5094577176 | D63: 1991-12-23 | E63: 34.5 | G63: Hot - logged | I63: 2
A64: B & C Heating & A/C | B64: Spokane | C64: 5099278861 | D64: 1992-07-23 | E64: 33.9 | G64: Hot - logged | I64: 2
A65: Vance Heating & Air Cond Inc | B65: Yakima | C65: 5092489450 | D65: 1993-09-17 | E65: 32.8 | F65: Yes | I65: 2
A66: Sammamish Heating & A/C | B66: Snohomish | C66: 4258819710 | D66: 1993-10-08 | E66: 32.7 | G66: Hot - logged | I66: 2
A67: Eaton'S Refrigeration | B67: Yakima | C67: 5095756340 | D67: 1994-07-01 | E67: 32 | G67: Hot - logged | I67: 2
A68: D & M Refrigeration Inc | B68: Spokane | C68: 5095359912 | D68: 1996-07-22 | E68: 29.9 | G68: Hot - logged | I68: 2
A69: Testcomm Llc | B69: Spokane | C69: 5095330498 | D69: 1996-11-12 | E69: 29.6 | G69: Skip - logged | I69: 2
A70: Choice Home Services Inc | B70: Snohomish | C70: 3605687900 | D70: 1997-01-31 | E70: 29.4 | G70: Hot - logged | I70: 2
A71: Keller Heating Inc | B71: Spokane | C71: 5099263551 | D71: 1999-04-26 | E71: 27.2 | G71: Hot - logged | H71: PASF intel 2026-07-02: GMB shows 4.3 stars / 6 reviews - low-review, L&I longevity path candidate (27-yr license) if no/weak website | I71: 2
A72: Z-Man Heating A/C Plmbg Srvcs | B72: Monroe | C72: 3607946594 | D72: 1999-12-22 | E72: 26.5 | G72: Hot - logged | I72: 2
A73: Delta Heating & Cooling Inc | B73: Richland | C73: 5099431092 | D73: 2000-01-19 | E73: 26.5 | G73: Skip - logged | I73: 2
A74: Wells & Wade Mechanical | B74: Wenatchee | C74: 5096623412 | D74: 2000-02-08 | E74: 26.4 | G74: Watch - logged | I74: 2
A75: Cozy Heating Inc | B75: Arlington | C75: 3604354904 | D75: 2000-02-09 | E75: 26.4 | F75: Yes | I75: 2
A76: Smith Mechanical Inc | B76: Ferndale | C76: 3603843203 | D76: 2000-02-14 | E76: 26.4 | F76: Yes | I76: 2
A77: Mccleary Htg & A/C Llc | B77: Spokane | C77: 5095355915 | D77: 2000-02-16 | E77: 26.4 | G77: Skip - logged | I77: 2
A78: Coffey Refrigeration | B78: Kennewick | C78: 5095861519 | D78: 2000-02-18 | E78: 26.4 | G78: Watch - logged | I78: 2
A79: Hilliard'S Htg & Plbg Inc | B79: Pullman | C79: 5093325713 | D79: 2000-02-22 | E79: 26.4 | G79: Skip - logged | I79: 2
A80: Advanced Energy Systems Inc | B80: Chehalis | C80: 3607481817 | D80: 2000-02-23 | E80: 26.4 | F80: Yes | I80: 2
A81: Olympia Sheet Metal Inc | B81: Tumwater | C81: 3604911123 | D81: 2000-02-23 | E81: 26.4 | G81: Skip - logged | I81: 2
A82: Andrews Mechanical Inc | B82: Spokane | C82: 5094893860 | D82: 2000-02-25 | E82: 26.3 | G82: Skip - logged | I82: 2
A83: Feller Heating & A/C Inc | B83: Bellingham | C83: 3607334827 | D83: 2000-02-25 | E83: 26.3 | G83: Skip - logged | I83: 2
A84: Air Flo Heating Co Inc | B84: Sequim | C84: 3606833901 | D84: 2000-02-28 | E84: 26.3 | F84: Yes | I84: 2
A85: Kollmar Inc | B85: Grandview | C85: 5098823148 | D85: 2000-02-28 | E85: 26.3 | G85: Skip - logged | I85: 2
A86: Marr'S Heating & A/C Inc | B86: Bellingham | C86: 3607469919 | D86: 2000-02-28 | E86: 26.3 | F86: Yes | G86: Imported (legacy) | I86: 2
A87: Moser Inc | B87: Spokane | C87: 5097470950 | D87: 2000-02-28 | E87: 26.3 | G87: Skip - logged | I87: 2
A88: Nickoloff Refrig Htg & A/C | B88: Yakima | C88: 5099521445 | D88: 2000-02-28 | E88: 26.3 | G88: Hot - logged | I88: 2
A89: Smith Heating & Cooling Inc | B89: Spokane | C89: 5093284431 | D89: 2000-02-28 | E89: 26.3 | G89: Warm - logged | I89: 2
A90: Robbins Air Inc | B90: Aberdeen | C90: 3605387003 | D90: 2000-02-29 | E90: 26.3 | F90: Yes | I90: 2
A91: Swanson'S Rfrgtn/Rest Rpr Inc | B91: Spokane | C91: 5099982870 | D91: 2000-02-29 | E91: 26.3 | G91: Skip - logged (name pre-filter) | I91: 2
A92: Team Mechanical Inc | B92: Monroe | C92: 3608051835 | D92: 2000-02-29 | E92: 26.3 | G92: Hot - logged | I92: 2
A93: Island Heating & A/C Inc | B93: Oak Harbor | C93: 3606791900 | D93: 2000-03-01 | E93: 26.3 | F93: Yes | I93: 2
A94: Polhamus Heating & A/C Inc | B94: Moses Lake | C94: 5097658524 | D94: 2000-03-06 | E94: 26.3 | G94: Skip - logged | I94: 2
A95: Tide Water Plbg & Mechanical | B95: Anacortes | C95: 3602011015 | D95: 2000-05-16 | E95: 26.1 | G95: Hot - logged | I95: 2
A96: Ben'S Heating Service Inc | B96: Port Townsend | C96: 3606433474 | D96: 2000-07-10 | E96: 26 | F96: Yes | I96: 2
A97: Bob Rhodes Heating And A/C Inc | B97: Kennewick | C97: 5097833291 | D97: 2000-07-17 | E97: 26 | G97: Imported (legacy) | I97: 2
A98: Platte Htg & A/C Inc | B98: Yakima | C98: 5099653538 | D98: 2000-08-31 | E98: 25.8 | G98: Hot - logged | I98: 2
A99: Horst Inc | B99: Pasco | C99: 5096270967 | D99: 2000-09-25 | E99: 25.8 | G99: Hot - logged | I99: 2
A100: Farwest Climate Control Inc | B100: Yakima | C100: 5094575346 | D100: 2001-01-02 | E100: 25.5 | G100: Skip - logged | I100: 2
...
